Workbook

Sheet SOV
A1: KENNY SENG CONSTRUCTION, INC.
A2: SCHEDULE OF VALUES
A4: Payment Request #5 | C4: Date: | D4: 46013 | E4: Job: Treasure Mountain Sports Complex
A6: ITEM | B6: DESCRIPTION OF WORK | C6: SCHEDULED | D6: WORK COMPLETED | F6: MATERIALS | G6: TOT COMPLETED | H6: % COMPLETE | I6: BALANCE TO
C7: VALUE | D7: PREVIOUS | E7: THIS PERIOD | F7: ON SITE | I7: FINISH
B8: ONSITE
A9: 1 | B9: =_xlfn.XLOOKUP(A9,Detail!A3:A654,Detail!C3:C654) -> Temporary Erosion & Sediment Control | C9: 40400 | D9: 12120 | E9: =+Detail!$K3 -> 2020 | F9: 0 | G9: =D9+E9+F9 -> 14140 | H9: =G9/C9 -> 0.35 | I9: =+C9-G9 -> 26260
A10: 2 | B10: =_xlfn.XLOOKUP(A10,Detail!A4:A655,Detail!C4:C655) -> Site Demolition | C10: 582300 | D10: 8086.3132 | E10: =+Detail!K6 -> 57531.748 | F10: 0 | G10: =D10+E10+F10 -> 65618.061 | H10: =G10/C10 -> 0.11268772 | I10: =+C10-G10 -> 516681.94
A11: 3 | B11: =_xlfn.XLOOKUP(A11,Detail!A6:A656,Detail!C6:C656) -> Site Earthwork | C11: 1267100 | D11: 509852.54 | E11: =+Detail!K85 -> 0 | F11: 0 | G11: =D11+E11+F11 -> 509852.54 | H11: =G11/C11 -> 0.40237751 | I11: =+C11-G11 -> 757247.46
A12: 4 | B12: =_xlfn.XLOOKUP(A12,Detail!A7:A657,Detail!C7:C657) -> Utilities (CW,FL,SD,SS,IRR) | C12: 1215500 | D12: 425292.36 | E12: =+Detail!K107 -> 0 | F12: 0 | G12: =D12+E12+F12 -> 425292.36 | H12: =G12/C12 -> 0.34989088 | I12: =+C12-G12 -> 790207.64
A13: 5 | B13: =_xlfn.XLOOKUP(A13,Detail!A9:A658,Detail!C9:C658) -> Building Earthwork | C13: 748900 | D13: 387693.95 | E13: =+Detail!K345 -> 99267.64 | F13: 0 | G13: =D13+E13+F13 -> 486961.59 | H13: =G13/C13 -> 0.6502358 | I13: =+C13-G13 -> 261938.41
A14: 6 | B14: =_xlfn.XLOOKUP(A14,Detail!A10:A659,Detail!C10:C659) -> Structural Concrete | C14: 317600 | D14: 103643.91 | E14: =+Detail!K376 -> 61201.961 | F14: 0 | G14: =D14+E14+F14 -> 164845.87 | H14: =G14/C14 -> 0.51903613 | I14: =+C14-G14 -> 152754.13
A15: 7 | B15: =_xlfn.XLOOKUP(A15,Detail!A11:A660,Detail!C11:C660) -> Site Concrete Prep | C15: 261500 | D15: 10633.273 | E15: =+Detail!K425 -> 0 | F15: 0 | G15: =D15+E15+F15 -> 10633.273 | H15: =G15/C15 -> 0.04066261 | I15: =+C15-G15 -> 250866.73
A16: 8 | B16: =_xlfn.XLOOKUP(A16,Detail!A12:A661,Detail!C12:C661) -> Site Concrete | C16: 1367500 | D16: 172106.44 | E16: =+Detail!K464 -> 0 | F16: 0 | G16: =D16+E16+F16 -> 172106.44 | H16: =G16/C16 -> 0.1258548 | I16: =+C16-G16 -> 1195393.6
A17: 9 | B17: =_xlfn.XLOOKUP(A17,Detail!A13:A662,Detail!C13:C662) -> Hot-Mix Asphalt (Prep) | C17: 130300 | D17: 0 | E17: =_xlfn.XLOOKUP(A17,Detail!$A$3:$A$654,Detail!$AE$3:$AE$654) -> 0 | F17: 0 | G17: =D17+E17+F17 -> 0 | H17: =G17/C17 -> 0 | I17: =+C17-G17 -> 130300
A18: 10 | B18: =_xlfn.XLOOKUP(A18,Detail!A14:A663,Detail!C14:C663) -> Hot-Mix Asphalt Paving | C18: 230200 | D18: 0 | E18: =_xlfn.XLOOKUP(A18,Detail!$A$3:$A$654,Detail!$AE$3:$AE$654) -> 0 | F18: 0 | G18: =D18+E18+F18 -> 0 | H18: =G18/C18 -> 0 | I18: =+C18-G18 -> 230200
A19: 11 | B19: =_xlfn.XLOOKUP(A19,Detail!A15:A664,Detail!C15:C664) -> Pavement Markings - Striping | C19: 2910 | D19: 0 | E19: =_xlfn.XLOOKUP(A19,Detail!$A$3:$A$654,Detail!$AE$3:$AE$654) -> 0 | F19: 0 | G19: =D19+E19+F19 -> 0 | H19: =G19/C19 -> 0 | I19: =+C19-G19 -> 2910
A20: 12 | B20: =_xlfn.XLOOKUP(A20,Detail!A16:A665,Detail!C16:C665) -> Exterior Sports Equipment | C20: 818500 | D20: 236740.89 | E20: =+Detail!K508 -> 0 | G20: =D20+E20+F20 -> 236740.89 | H20: =G20/C20 -> 0.2892375 | I20: =+C20-G20 -> 581759.11
A21: 13 | B21: =_xlfn.XLOOKUP(A21,Detail!A17:A666,Detail!C17:C666) -> Turf Field Prep | C21: 2424100 | D21: 1091650.8 | E21: =+Detail!K600 -> 0 | F21: 0 | G21: =D21+E21+F21 -> 1091650.8 | H21: =G21/C21 -> 0.4503324 | I21: =+C21-G21 -> 1332449.2
A22: 14 | B22: =_xlfn.XLOOKUP(A22,Detail!A18:A667,Detail!C18:C667) -> Segmented Retaining Wall | C22: 63300 | D22: 63300 | E22: =+Detail!P627 -> 0 | F22: 0 | G22: =D22+E22+F22 -> 63300 | H22: =G22/C22 -> 1 | I22: =+C22-G22 -> 0
A23: 15 | B23: =_xlfn.XLOOKUP(A23,Detail!A19:A668,Detail!C19:C668) -> Concrete Sign Wall - Tilt Panel | C23: 24700 | D23: 0 | E23: =_xlfn.XLOOKUP(A23,Detail!$A$3:$A$654,Detail!$AE$3:$AE$654) -> 0 | F23: 0 | G23: =D23+E23+F23 -> 0 | H23: =G23/C23 -> 0 | I23: =+C23-G23 -> 24700
A24: 16 | B24: =_xlfn.XLOOKUP(A24,Detail!A20:A669,Detail!C20:C669) -> Baseball & Softball Scoreboards | C24: 63000 | D24: 0 | E24: =_xlfn.XLOOKUP(A24,Detail!$A$3:$A$654,Detail!$AE$3:$AE$654) -> 0 | F24: 0 | G24: =D24+E24+F24 -> 0 | H24: =G24/C24 -> 0 | I24: =+C24-G24 -> 63000
A25: 17 | B25: =_xlfn.XLOOKUP(A25,Detail!A21:A670,Detail!C21:C670) -> Soccer Scoreboards | C25: 65000 | D25: 0 | E25: =_xlfn.XLOOKUP(A25,Detail!$A$3:$A$654,Detail!$AE$3:$AE$654) -> 0 | F25: 0 | G25: =D25+E25+F25 -> 0 | H25: =G25/C25 -> 0 | I25: =+C25-G25 -> 65000
A26: 18 | B26: =_xlfn.XLOOKUP(A26,Detail!A22:A671,Detail!C22:C671) -> Building Demo (Concrete Slabs And Footings) | C26: 398000 | D26: 0 | E26: =+Detail!K648 -> 9045.4545 | F26: 0 | G26: =D26+E26+F26 -> 9045.4545 | H26: =G26/C26 -> 0.022727273 | I26: =+C26-G26 -> 388954.55
A27: 19 | B27: =_xlfn.XLOOKUP(A27,Detail!A23:A672,Detail!C23:C672) -> Hazwoper Training | C27: 100000 | D27: 35000 | E27: 15000 | F27: 0 | G27: =D27+E27+F27 -> 50000 | H27: =G27/C27 -> 0.5 | I27: =+C27-G27 -> 50000
B28: SUBTOTAL | C28: =SUM(C9:C27) -> 10120810 | D28: =SUM(D9:D27) -> 3056120.4 | E28: =SUM(E9:E27) -> 244066.8 | F28: =SUM(F9:F27) -> 0 | G28: =SUM(G9:G27) -> 3300187.3 | H28: =G28/C28 -> 0.32607936 | I28: =SUM(I9:I27) -> 6820622.7
B29: Change Orders
C30: 0 | D30: 0 | E30: 0 | F30: 0 | G30: =D30+E30+F30 -> 0 | H30: =IF(B30="","",(G30/C30)) | I30: =+C30-G30 -> 0
C31: 0 | D31: 0 | E31: 0 | F31: 0 | G31: =D31+E31+F31 -> 0 | H31: =IF(B31="","",(G31/C31)) | I31: =+C31-G31 -> 0
B32: SUBTOTAL | C32: =SUM(C30:C31) -> 0 | D32: =SUM(D30:D31) -> 0 | E32: =SUM(E30:E31) -> 0 | F32: =SUM(F30:F31) -> 0 | G32: =SUM(G30:G31) -> 0 | H32: =IF(B30="","",(G32/C32)) | I32: =SUM(I30:I31) -> 0
B33: TOTALS | C33: =+C32+C28 -> 10120810 | D33: =+D32+D28 -> 3056120.4 | E33: =+E32+E28 -> 244066.8 | F33: =+F32+F28 -> 0 | G33: =+G32+G28 -> 3300187.3 | H33: =G33/C33 -> 0.32607936 | I33: =+C33-G33 -> 6820622.7
C36: 10120810 | D36: 2411787.8 | E36: 532332.62 | F36: 0 | G36: 2944120.4 | H36: 0.29089771 | I36: 7176689.6

Sheet Detail
A1: ITEM | B1: PHASE | C1: DESCRIPTION OF WORK | D1: SCHEDULED VALUE | E1: COST | F1: PRICE | G1: QTY | H1: UOM | I1: UNIT PRICE | J1: 46016 | O1: 45986 | T1: 45955 | Y1: 45925 | AD1: 45894
J2: QTY | K2: AMT | L2: REM | M2: Rem Qty | N2: % Com | O2: QTY | P2: AMT | Q2: REM | R2: Rem Qty | S2: % Com | T2: QTY | U2: AMT | V2: REM | W2: Rem Qty | X2: % Com | Y2: QTY | Z2: AMT | AA2: REM | AB2: Rem Qty | AC2: % Com | AD2: QTY | AE2: AMT | AF2: REM | AG2: Rem Qty | AH2: % Com
A3: 1 | C3: Temporary Erosion & Sediment Control | D3: =_xlfn.XLOOKUP(A3,SOV!$A$9:$A$27,SOV!$C$9:$C$27) -> 40400 | E3: 29138.08 | F3: =SUM(F4) -> 40400 | K3: =SUM(K4) -> 2020 | L3: =+Q3-K4 -> 26260 | P3: =SUM(P4) -> 2020 | Q3: =+V3-P4 -> 28280 | U3: =SUM(U4) -> 2020 | V3: =+AA3-U4 -> 30300 | Z3: =SUM(Z4) -> 2020 | AA3: =SUM(AA4) -> 32320 | AE3: =SUM(AE4) -> 6060 | AF3: =SUM(AF4) -> 34340
C4: SWPPP | E4: 29138.08 | F4: =$D$3/$E$3*E4 -> 40400 | G4: 1 | H4: LS | I4: =F4/G4 -> 40400 | J4: 0.05 | K4: =+J4*$I4 -> 2020 | L4: =+Q4-K4 -> 26260 | M4: =+R4-J4 -> 0.65 | N4: =100%-(L4/$F4) -> 0.35 | O4: 0.05 | P4: =+O4*$I4 -> 2020 | Q4: =+V4-P4 -> 28280 | R4: =+W4-O4 -> 0.7 | S4: =100%-(Q4/$F4) -> 0.3 | T4: 0.05 | U4: =+T4*$I4 -> 2020 | V4: =+AA4-U4 -> 30300 | W4: =+AB4-T4 -> 0.75 | X4: =100%-(V4/$F4) -> 0.25 | Y4: 0.05 | Z4: =Y4*I4 -> 2020 | AA4: =+AF4-Z4 -> 32320 | AB4: =+AG4-Y4 -> 0.8 | AC4: =100%-(AA4/$F4) -> 0.2 | AD4: 0.15 | AE4: =AD4*I4 -> 6060 | AF4: =F4-AE4 -> 34340 | AG4: =G4-AD4 -> 0.85 | AH4: =100%-(AF4/$F4) -> 0.15
B5: 2100 | C5: SWPPP | E5: 29138.08 | F5: =$D$3/$E$3*E5 -> 40400 | G5: 1 | H5: LS | I5: =F5/G5 -> 40400 | J5: =J4 -> 0.05 | L5: =+Q5-K5 -> 0 | O5: =O4 -> 0.05 | Q5: =+V5-P5 -> 0 | T5: =T4 -> 0.05 | V5: =+AA5-U5 -> 0 | Y5: =Y4 -> 0.05 | AA5: =+AF5-Z5 -> 0 | AD5: =AD4 -> 0.15
A6: 2 | C6: Site Demolition | D6: =_xlfn.XLOOKUP(A6,SOV!$A$9:$A$27,SOV!$C$9:$C$27) -> 582300 | E6: 422513.36 | F6: =SUM(F7,F9,F13,F17,F21,F25,F33,F41,F45,F49,F53,F61,F65,F69,F77,F81) -> 582299.99 | K6: =SUM(K7:K84) -> 57531.748 | L6: =SUM(L7:L81) -> 516681.93 | P6: =SUM(P7:P84) -> 0 | Q6: =SUM(Q7:Q81) -> 574213.67 | U6: =SUM(U7:U84) -> 0 | V6: =SUM(V7:V81) -> 574213.67 | Z6: =SUM(Z7:Z84) -> 1164.5632 | AA6: =+AF6-Z6 -> 574213.67 | AE6: =SUM(AE7:AE84) -> 6921.7501 | AF6: =SUM(AF7:AF84) -> 575378.24
C7: Tree Removal | E7: 16900 | F7: =$D$6/$E$6*E7 -> 23291.263 | G7: 1 | H7: LS | I7: =F7/G7 -> 23291.263 | J7: 0.75 | K7: =+J7*$I7 -> 17468.448 | L7: =+Q7-K7 -> 1164.5632 | M7: =+R7-J7 -> 0.05 | N7: =100%-(L7/$F7) -> 0.95 | P7: =O7*I7 -> 0 | Q7: =+V7-P7 -> 18633.011 | R7: =+W7-O7 -> 0.8 | S7: =100%-(Q7/$F7) -> 0.2 | U7: =T7*D7 -> 0 | V7: =+AA7-U7 -> 18633.011 | W7: =+AB7-T7 -> 0.8 | X7: =100%-(V7/$F7) -> 0.2 | Y7: 0.05 | Z7: =Y7*I7 -> 1164.5632 | AA7: =+AF7-Z7 -> 18633.011 | AB7: =+AG7-Y7 -> 0.8 | AC7: =100%-(AA7/$F7) -> 0.2 | AD7: 0.15 | AE7: =AD7*I7 -> 3493.6895 | AF7: =F7-AE7 -> 19797.574 | AG7: =G7-AD7 -> 0.85 | AH7: =100%-(AF7/$F7) -> 0.15
B8: 2402 | C8: Tree Removal | E8: 16900 | F8: =$D$6/$E$6*E8 -> 23291.263 | G8: 1 | H8: LS | I8: =F8/G8 -> 23291.263 | K8: =+J8*$I8 -> 0 | L8: =+Q8-K8 -> 0 | M8: =+R8-J8 -> 0 | P8: =O8*I8 -> 0 | Q8: =+V8-P8 -> 0 | R8: =+W8-O8 -> 0 | U8: =T8*D8 -> 0 | V8: =+AA8-U8 -> 0 | W8: =+AB8-T8 -> 0 | Z8: =Y8*I8 -> 0 | AA8: =+AF8-Z8 -> 0 | AB8: =+AG8-Y8 -> 0 | AD8: =AD7 -> 0.15
C9: Remove Concrete Flatwork 04" | E9: 16075.12 | F9: =$D$6/$E$6*E9 -> 22154.429 | G9: 17303 | H9: SF | I9: =F9/G9 -> 1.2803808 | J9: 8003 | K9: =+J9*$I9 -> 10246.888 | L9: =+Q9-K9 -> 11907.542 | M9: =+R9-J9 -> 9300 | N9: =100%-(L9/$F9) -> 0.46252095 | O9: 0 | P9: =O9*I9 -> 0 | Q9: =+V9-P9 -> 22154.429 | R9: =+W9-O9 -> 17303 | S9: =100%-(Q9/$F9) -> 0 | T9: 0 | U9: =T9*D9 -> 0 | V9: =+AA9-U9 -> 22154.429 | W9: =+AB9-T9 -> 17303 | X9: =100%-(V9/$F9) -> 0 | Y9: 0 | Z9: =Y9*I9 -> 0 | AA9: =+AF9-Z9 -> 22154.429 | AB9: =+AG9-Y9 -> 17303 | AC9: =100%-(AA9/$F9) -> 0 | AD9: 0 | AE9: =AD9*I9 -> 0 | AF9: =F9-AE9 -> 22154.429 | AG9: =G9-AD9 -> 17303 | AH9: =100%-(AF9/$F9) -> 0
B10: 2420 | C10: Remove Concrete Flatwork | E10: 6663.73 | F10: =$D$6/$E$6*E10 -> 9183.8279 | G10: 17303 | H10: SF | I10: =F10/G10 -> 0.53076506 | K10: =+J10*$I10 -> 0 | L10: =+Q10-K10 -> 0 | M10: =+R10-J10 -> 0 | P10: =O10*I10 -> 0 | Q10: =+V10-P10 -> 0 | R10: =+W10-O10 -> 0 | U10: =T10*D10 -> 0 | V10: =+AA10-U10 -> 0 | W10: =+AB10-T10 -> 0 | Y10: =$AD$9*B10/$G$9 -> 0 | Z10: =Y10*I10 -> 0 | AA10: =+AF10-Z10 -> 0 | AB10: =+AG10-Y10 -> 0 | AD10: =$AD$9*G10/$G$9 -> 0
B11: 2490 | C11: Dump Fees | E11: 2850.67 | F11: =$D$6/$E$6*E11 -> 3928.74 | G11: 432.58 | H11: TON | I11: =F11/G11 -> 9.082112 | K11: =+J11*$I11 -> 0 | L11: =+Q11-K11 -> 0 | M11: =+R11-J11 -> 0 | P11: =O11*I11 -> 0 | Q11: =+V11-P11 -> 0 | R11: =+W11-O11 -> 0 | U11: =T11*D11 -> 0 | V11: =+AA11-U11 -> 0 | W11: =+AB11-T11 -> 0 | Y11: =$AD$9*B11/$G$9 -> 0 | Z11: =Y11*I11 -> 0 | AA11: =+AF11-Z11 -> 0 | AB11: =+AG11-Y11 -> 0 | AD11: =$AD$9*G11/$G$9 -> 0
B12: 2150 | C12: Export Trucking | E12: 6560.72 | F12: =$D$6/$E$6*E12 -> 9041.8614 | G12: 432.58 | H12: TON | I12: =F12/G12 -> 20.902172 | K12: =+J12*$I12 -> 0 | L12: =+Q12-K12 -> 0 | M12: =+R12-J12 -> 0 | P12: =O12*I12 -> 0 | Q12: =+V12-P12 -> 0 | R12: =+W12-O12 -> 0 | U12: =T12*D12 -> 0 | V12: =+AA12-U12 -> 0 | W12: =+AB12-T12 -> 0 | Y12: =$AD$9*B12/$G$9 -> 0 | Z12: =Y12*I12 -> 0 | AA12: =+AF12-Z12 -> 0 | AB12: =+AG12-Y12 -> 0 | AD12: =$AD$9*G12/$G$9 -> 0
C13: Remove Asphalt SF (03") | E13: 98784.18 | F13: =$D$6/$E$6*E13 -> 136142.51 | G13: 147064 | H13: SF | I13: =F13/G13 -> 0.92573646 | J13: 25731 | K13: =+J13*$I13 -> 23820.125 | L13: =+Q13-K13 -> 112322.38 | M13: =+R13-J13 -> 121333 | N13: =100%-(L13/$F13) -> 0.17496464 | P13: =O13*I13 -> 0 | Q13: =+V13-P13 -> 136142.51 | R13: =+W13-O13 -> 147064 | S13: =100%-(Q13/$F13) -> 0 | U13: =T13*D13 -> 0 | V13: =+AA13-U13 -> 136142.51 | W13: =+AB13-T13 -> 147064 | X13: =100%-(V13/$F13) -> 0 | Z13: =Y13*I13 -> 0 | AA13: =+AF13-Z13 -> 136142.51 | AB13: =+AG13-Y13 -> 147064 | AC13: =100%-(AA13/$F13) -> 0 | AE13: =AD13*I13 -> 0 | AF13: =F13-AE13 -> 136142.51 | AG13: =G13-AD13 -> 147064 | AH13: =100%-(AF13/$F13) -> 0
B14: 2410 | C14: Remove Asphalt | E14: 39646.07 | F14: =$D$6/$E$6*E14 -> 54639.471 | G14: 147064 | H14: SF | I14: =F14/G14 -> 0.37153533 | K14: =+J14*$I14 -> 0 | L14: =+Q14-K14 -> 0 | M14: =+R14-J14 -> 0 | P14: =O14*I14 -> 0 | Q14: =+V14-P14 -> 0 | R14: =+W14-O14 -> 0 | U14: =T14*D14 -> 0 | V14: =+AA14-U14 -> 0 | W14: =+AB14-T14 -> 0 | Y14: =$AD$13*B14/$G$13 -> 0 | Z14: =Y14*I14 -> 0 | AA14: =+AF14-Z14 -> 0 | AB14: =+AG14-Y14 -> 0 | AD14: =$AD$13*G14/$G$13 -> 0
B15: 2490 | C15: Dump Fees | E15: 17316.79 | F15: =$D$6/$E$6*E15 -> 23865.676 | G15: 2757.45 | H15: TON | I15: =F15/G15 -> 8.6549804 | K15: =+J15*$I15 -> 0 | L15: =+Q15-K15 -> 0 | M15: =+R15-J15 -> 0 | P15: =O15*I15 -> 0 | Q15: =+V15-P15 -> 0 | R15: =+W15-O15 -> 0 | U15: =T15*D15 -> 0 | V15: =+AA15-U15 -> 0 | W15: =+AB15-T15 -> 0 | Y15: =$AD$13*B15/$G$13 -> 0 | Z15: =Y15*I15 -> 0 | AA15: =+AF15-Z15 -> 0 | AB15: =+AG15-Y15 -> 0 | AD15: =$AD$13*G15/$G$13 -> 0
B16: 2150 | C16: Export Trucking | E16: 41821.33 | F16: =$D$6/$E$6*E16 -> 57637.374 | G16: 2757.45 | H16: TON | I16: =F16/G16 -> 20.902418 | K16: =+J16*$I16 -> 0 | L16: =+Q16-K16 -> 0 | M16: =+R16-J16 -> 0 | P16: =O16*I16 -> 0 | Q16: =+V16-P16 -> 0 | R16: =+W16-O16 -> 0 | U16: =T16*D16 -> 0 | V16: =+AA16-U16 -> 0 | W16: =+AB16-T16 -> 0 | Y16: =$AD$13*B16/$G$13 -> 0 | Z16: =Y16*I16 -> 0 | AA16: =+AF16-Z16 -> 0 | AB16: =+AG16-Y16 -> 0 | AD16: =$AD$13*G16/$G$13 -> 0
C17: Remove Curb/Gutter 24" | E17: 11787.9 | F17: =$D$6/$E$6*E17 -> 16245.863 | G17: 1634 | H17: LF | I17: =F17/G17 -> 9.9423886 | K17: =+J17*$I17 -> 0 | L17: =+Q17-K17 -> 16245.863 | M17: =+R17-J17 -> 1634 | N17: =100%-(L17/$F17) -> 0 | P17: =O17*I17 -> 0 | Q17: =+V17-P17 -> 16245.863 | R17: =+W17-O17 -> 1634 | S17: =100%-(Q17/$F17) -> 0 | U17: =T17*D17 -> 0 | V17: =+AA17-U17 -> 16245.863 | W17: =+AB17-T17 -> 1634 | X17: =100%-(V17/$F17) -> 0 | Z17: =Y17*I17 -> 0 | AA17: =+AF17-Z17 -> 16245.863 | AB17: =+AG17-Y17 -> 1634 | AC17: =100%-(AA17/$F17) -> 0 | AE17: =AD17*I17 -> 0 | AF17: =F17-AE17 -> 16245.863 | AG17: =G17-AD17 -> 1634 | AH17: =100%-(AF17/$F17) -> 0
B18: 2421 | C18: Remove Curb And Gutter | E18: 7521.86 | F18: =$D$6/$E$6*E18 -> 10366.487 | G18: 1634 | H18: LF | I18: =F18/G18 -> 6.344239 | K18: =+J18*$I18 -> 0 | L18: =+Q18-K18 -> 0 | M18: =+R18-J18 -> 0 | P18: =O18*I18 -> 0 | Q18: =+V18-P18 -> 0 | R18: =+W18-O18 -> 0 | U18: =T18*D18 -> 0 | V18: =+AA18-U18 -> 0 | W18: =+AB18-T18 -> 0 | Y18: =$AD$17*B18/$G$17 -> 0 | Z18: =Y18*I18 -> 0 | AA18: =+AF18-Z18 -> 0 | AB18: =+AG18-Y18 -> 0 | AD18: =$AD$17*G18/$G$17 -> 0
B19: 2490 | C19: Dump Fees | E19: 1292.17 | F19: =$D$6/$E$6*E19 -> 1780.8445 | G19: 196.08 | H19: TON | I19: =F19/G19 -> 9.0822343 | K19: =+J19*$I19 -> 0 | L19: =+Q19-K19 -> 0 | M19: =+R19-J19 -> 0 | P19: =O19*I19 -> 0 | Q19: =+V19-P19 -> 0 | R19: =+W19-O19 -> 0 | U19: =T19*D19 -> 0 | V19: =+AA19-U19 -> 0 | W19: =+AB19-T19 -> 0 | Y19: =$AD$17*B19/$G$17 -> 0 | Z19: =Y19*I19 -> 0 | AA19: =+AF19-Z19 -> 0 | AB19: =+AG19-Y19 -> 0 | AD19: =$AD$17*G19/$G$17 -> 0
B20: 2150 | C20: Export Trucking | E20: 2973.88 | F20: =$D$6/$E$6*E20 -> 4098.5457 | G20: 196.08 | H20: TON | I20: =F20/G20 -> 20.902416 | K20: =+J20*$I20 -> 0 | L20: =+Q20-K20 -> 0 | M20: =+R20-J20 -> 0 | P20: =O20*I20 -> 0 | Q20: =+V20-P20 -> 0 | R20: =+W20-O20 -> 0 | U20: =T20*D20 -> 0 | V20: =+AA20-U20 -> 0 | W20: =+AB20-T20 -> 0 | Y20: =$AD$17*B20/$G$17 -> 0 | Z20: =Y20*I20 -> 0 | AA20: =+AF20-Z20 -> 0 | AB20: =+AG20-Y20 -> 0 | AD20: =$AD$17*G20/$G$17 -> 0
C21: Remove Chain Link Fence | E21: 2487.38 | F21: =$D$6/$E$6*E21 -> 3428.0605 | G21: 811 | H21: LF | I21: =F21/G21 -> 4.226955 | K21: =+J21*$I21 -> 0 | L21: =+Q21-K21 -> 0 | M21: =+R21-J21 -> 0 | N21: =100%-(L21/$F21) -> 1 | P21: =O21*I21 -> 0 | Q21: =+V21-P21 -> 0 | R21: =+W21-O21 -> 0 | S21: =100%-(Q21/$F21) -> 1 | U21: =T21*D21 -> 0 | V21: =+AA21-U21 -> 0 | W21: =+AB21-T21 -> 0 | X21: =100%-(V21/$F21) -> 1 | Z21: =Y21*I21 -> 0 | AA21: =+AF21-Z21 -> 0 | AB21: =+AG21-Y21 -> 0 | AC21: =100%-(AA21/$F21) -> 1 | AD21: 811 | AE21: =AD21*I21 -> 3428.0605 | AF21: =F21-AE21 -> 0 | AG21: =G21-AD21 -> 0 | AH21: =100%-(AF21/$F21) -> 1
B22: 2401 | C22: Remove Fence | E22: 2421.99 | F22: =$D$6/$E$6*E22 -> 3337.9413 | G22: 811 | H22: LF | I22: =F22/G22 -> 4.1158339 | K22: =+J22*$I22 -> 0 | L22: =+Q22-K22 -> 0 | M22: =+R22-J22 -> 0 | P22: =O22*I22 -> 0 | Q22: =+V22-P22 -> 0 | R22: =+W22-O22 -> 0 | U22: =T22*D22 -> 0 | V22: =+AA22-U22 -> 0 | W22: =+AB22-T22 -> 0 | Z22: =Y22*I22 -> 0 | AA22: =+AF22-Z22 -> 0 | AB22: =+AG22-Y22 -> 0 | AD22: =$AD$21*G22/$G$21 -> 811
B23: 2490 | C23: Dump Fees | E23: 50.69 | F23: =$D$6/$E$6*E23 -> 69.860009 | G23: 2.03 | H23: TON | I23: =F23/G23 -> 34.413797 | K23: =+J23*$I23 -> 0 | L23: =+Q23-K23 -> 0 | M23: =+R23-J23 -> 0 | P23: =O23*I23 -> 0 | Q23: =+V23-P23 -> 0 | R23: =+W23-O23 -> 0 | U23: =T23*D23 -> 0 | V23: =+AA23-U23 -> 0 | W23: =+AB23-T23 -> 0 | Z23: =Y23*I23 -> 0 | AA23: =+AF23-Z23 -> 0 | AB23: =+AG23-Y23 -> 0 | AD23: =$AD$21*G23/$G$21 -> 2.03
B24: 2150 | C24: Export Trucking | E24: 14.71 | F24: =$D$6/$E$6*E24 -> 20.273047 | G24: 2.03 | H24: TON | I24: =F24/G24 -> 9.9867224 | K24: =+J24*$I24 -> 0 | L24: =+Q24-K24 -> 0 | M24: =+R24-J24 -> 0 | P24: =O24*I24 -> 0 | Q24: =+V24-P24 -> 0 | R24: =+W24-O24 -> 0 | U24: =T24*D24 -> 0 | V24: =+AA24-U24 -> 0 | W24: =+AB24-T24 -> 0 | Z24: =Y24*I24 -> 0 | AA24: =+AF24-Z24 -> 0 | AB24: =+AG24-Y24 -> 0 | AD24: =$AD$21*G24/$G$21 -> 2.03
C25: Remove PVC Pipe (08") WATER | E25: 159088.02 | F25: =$D$6/$E$6*E25 -> 219252.13 | G25: 3367 | H25: LF | I25: =F25/G25 -> 65.117948 | J25: 0 | K25: =+J25*$I25 -> 0 | L25: =+Q25-K25 -> 219252.13 | M25: =+R25-J25 -> 3367 | N25: =100%-(L25/$F25) -> 0 | O25: 0 | P25: =O25*I25 -> 0 | Q25: =+V25-P25 -> 219252.13 | R25: =+W25-O25 -> 3367 | S25: =100%-(Q25/$F25) -> 0 | T25: 0 | U25: =T25*D25 -> 0 | V25: =+AA25-U25 -> 219252.13 | W25: =+AB25-T25 -> 3367 | X25: =100%-(V25/$F25) -> 0 | Y25: 0 | Z25: =Y25*I25 -> 0 | AA25: =+AF25-Z25 -> 219252.13 | AB25: =+AG25-Y25 -> 3367 | AC25: =100%-(AA25/$F25) -> 0 | AD25: 0 | AE25: =AD25*I25 -> 0 | AF25: =F25-AE25 -> 219252.13 | AG25: =G25-AD25 -> 3367 | AH25: =100%-(AF25/$F25) -> 0
B26: 2450 | C26: Remove Pipe | E26: 130624.04 | F26: =$D$6/$E$6*E26 -> 180023.61 | G26: 3367 | H26: LF | I26: =F26/G26 -> 53.467064 | K26: =+J26*$I26 -> 0 | L26: =+Q26-K26 -> 0 | M26: =+R26-J26 -> 0 | P26: =O26*I26 -> 0 | Q26: =+V26-P26 -> 0 | R26: =+W26-O26 -> 0 | U26: =T26*D26 -> 0 | V26: =+AA26-U26 -> 0 | W26: =+AB26-T26 -> 0 | Y26: =$AD$25*B26/$G$25 -> 0 | Z26: =Y26*I26 -> 0 | AA26: =+AF26-Z26 -> 0 | AB26: =+AG26-Y26 -> 0 | AD26: =$AD$25*G26/$G$25 -> 0
B27: 2490 | C27: Dump Fees | E27: 480.64 | F27: =$D$6/$E$6*E27 -> 662.40905 | G27: 19.23 | H27: TON | I27: =F27/G27 -> 34.446648 | K27: =+J27*$I27 -> 0 | L27: =+Q27-K27 -> 0 | M27: =+R27-J27 -> 0 | P27: =O27*I27 -> 0 | Q27: =+V27-P27 -> 0 | R27: =+W27-O27 -> 0 | U27: =T27*D27 -> 0 | V27: =+AA27-U27 -> 0 | W27: =+AB27-T27 -> 0 | Y27: =$AD$25*B27/$G$25 -> 0 | Z27: =Y27*I27 -> 0 | AA27: =+AF27-Z27 -> 0 | AB27: =+AG27-Y27 -> 0 | AD27: =$AD$25*G27/$G$25 -> 0
B28: 2150 | C28: Export Trucking | E28: 139.46 | F28: =$D$6/$E$6*E28 -> 192.20116 | G28: 19.23 | H28: TON | I28: =F28/G28 -> 9.9948601 | K28: =+J28*$I28 -> 0 | L28: =+Q28-K28 -> 0 | M28: =+R28-J28 -> 0 | P28: =O28*I28 -> 0 | Q28: =+V28-P28 -> 0 | R28: =+W28-O28 -> 0 | U28: =T28*D28 -> 0 | V28: =+AA28-U28 -> 0 | W28: =+AB28-T28 -> 0 | Y28: =$AD$25*B28/$G$25 -> 0 | Z28: =Y28*I28 -> 0 | AA28: =+AF28-Z28 -> 0 | AB28: =+AG28-Y28 -> 0 | AD28: =$AD$25*G28/$G$25 -> 0
B29: 2172 | C29: Import Efill | E29: 8464.11 | F29: =$D$6/$E$6*E29 -> 11665.078 | G29: 971.1 | H29: TON | I29: =F29/G29 -> 12.012231 | K29: =+J29*$I29 -> 0 | L29: =+Q29-K29 -> 0 | M29: =+R29-J29 -> 0 | P29: =O29*I29 -> 0 | Q29: =+V29-P29 -> 0 | R29: =+W29-O29 -> 0 | U29: =T29*D29 -> 0 | V29: =+AA29-U29 -> 0 | W29: =+AB29-T29 -> 0 | Y29: =$AD$25*B29/$G$25 -> 0 | Z29: =Y29*I29 -> 0 | AA29: =+AF29-Z29 -> 0 | AB29: =+AG29-Y29 -> 0 | AD29: =$AD$25*G29/$G$25 -> 0
B30: 2149 | C30: Import Trucking | E30: 8233.24 | F30: =$D$6/$E$6*E30 -> 11346.897 | G30: 971.1 | H30: TON | I30: =F30/G30 -> 11.684582 | K30: =+J30*$I30 -> 0 | L30: =+Q30-K30 -> 0 | M30: =+R30-J30 -> 0 | P30: =O30*I30 -> 0 | Q30: =+V30-P30 -> 0 | R30: =+W30-O30 -> 0 | U30: =T30*D30 -> 0 | V30: =+AA30-U30 -> 0 | W30: =+AB30-T30 -> 0 | Y30: =$AD$25*B30/$G$25 -> 0 | Z30: =Y30*I30 -> 0 | AA30: =+AF30-Z30 -> 0 | AB30: =+AG30-Y30 -> 0 | AD30: =$AD$25*G30/$G$25 -> 0
B31: 2150 | C31: Export Trucking | E31: 8233.24 | F31: =$D$6/$E$6*E31 -> 11346.897 | G31: 971.1 | H31: TON | I31: =F31/G31 -> 11.684582 | K31: =+J31*$I31 -> 0 | L31: =+Q31-K31 -> 0 | M31: =+R31-J31 -> 0 | P31: =O31*I31 -> 0 | Q31: =+V31-P31 -> 0 | R31: =+W31-O31 -> 0 | U31: =T31*D31 -> 0 | V31: =+AA31-U31 -> 0 | W31: =+AB31-T31 -> 0 | Y31: =$AD$25*B31/$G$25 -> 0 | Z31: =Y31*I31 -> 0 | AA31: =+AF31-Z31 -> 0 | AB31: =+AG31-Y31 -> 0 | AD31: =$AD$25*G31/$G$25 -> 0
B32: 2490 | C32: Dump Fees | E32: 2913.3 | F32: =$D$6/$E$6*E32 -> 4015.0555 | G32: 971.1 | H32: TON | I32: =F32/G32 -> 4.1345438 | K32: =+J32*$I32 -> 0 | L32: =+Q32-K32 -> 0 | M32: =+R32-J32 -> 0 | P32: =O32*I32 -> 0 | Q32: =+V32-P32 -> 0 | R32: =+W32-O32 -> 0 | U32: =T32*D32 -> 0 | V32: =+AA32-U32 -> 0 | W32: =+AB32-T32 -> 0 | Y32: =$AD$25*B32/$G$25 -> 0 | Z32: =Y32*I32 -> 0 | AA32: =+AF32-Z32 -> 0 | AB32: =+AG32-Y32 -> 0 | AD32: =$AD$25*G32/$G$25 -> 0
C33: Remove PVC Pipe (08") SEWER | E33: 63206.44 | F33: =$D$6/$E$6*E33 -> 87109.932 | G33: 691 | H33: LF | I33: =F33/G33 -> 126.06358 | K33: =+J33*$I33 -> 0 | L33: =+Q33-K33 -> 87109.932 | M33: =+R33-J33 -> 691 | N33: =100%-(L33/$F33) -> 0 | P33: =O33*I33 -> 0 | Q33: =+V33-P33 -> 87109.932 | R33: =+W33-O33 -> 691 | S33: =100%-(Q33/$F33) -> 0 | U33: =T33*D33 -> 0 | V33: =+AA33-U33 -> 87109.932 | W33: =+AB33-T33 -> 691 | X33: =100%-(V33/$F33) -> 0 | Z33: =Y33*I33 -> 0 | AA33: =+AF33-Z33 -> 87109.932 | AB33: =+AG33-Y33 -> 691 | AC33: =100%-(AA33/$F33) -> 0 | AE33: =AD33*I33 -> 0 | AF33: =F33-AE33 -> 87109.932 | AG33: =G33-AD33 -> 691 | AH33: =100%-(AF33/$F33) -> 0
B34: 2450 | C34: Remove Pipe | E34: 40211.41 | F34: =$D$6/$E$6*E34 -> 55418.612 | G34: 691 | H34: LF | I34: =F34/G34 -> 80.200597 | K34: =+J34*$I34 -> 0 | L34: =+Q34-K34 -> 0 | M34: =+R34-J34 -> 0 | P34: =O34*I34 -> 0 | Q34: =+V34-P34 -> 0 | R34: =+W34-O34 -> 0 | U34: =T34*D34 -> 0 | V34: =+AA34-U34 -> 0 | W34: =+AB34-T34 -> 0 | Y34: =$AD$33*B34/$G$33 -> 0 | Z34: =Y34*I34 -> 0 | AA34: =+AF34-Z34 -> 0 | AB34: =+AG34-Y34 -> 0 | AD34: =$AD$33*G34/$G$33 -> 0
B35: 2490 | C35: Dump Fees | E35: 98.64 | F35: =$D$6/$E$6*E35 -> 135.9438 | G35: 3.95 | H35: TON | I35: =F35/G35 -> 34.416152 | K35: =+J35*$I35 -> 0 | L35: =+Q35-K35 -> 0 | M35: =+R35-J35 -> 0 | P35: =O35*I35 -> 0 | Q35: =+V35-P35 -> 0 | R35: =+W35-O35 -> 0 | U35: =T35*D35 -> 0 | V35: =+AA35-U35 -> 0 | W35: =+AB35-T35 -> 0 | Y35: =$AD$33*B35/$G$33 -> 0 | Z35: =Y35*I35 -> 0 | AA35: =+AF35-Z35 -> 0 | AB35: =+AG35-Y35 -> 0 | AD35: =$AD$33*G35/$G$33 -> 0
B36: 2150 | C36: Export Trucking | E36: 28.62 | F36: =$D$6/$E$6*E36 -> 39.443548 | G36: 3.95 | H36: TON | I36: =F36/G36 -> 9.9857084 | K36: =+J36*$I36 -> 0 | L36: =+Q36-K36 -> 0 | M36: =+R36-J36 -> 0 | P36: =O36*I36 -> 0 | Q36: =+V36-P36 -> 0 | R36: =+W36-O36 -> 0 | U36: =T36*D36 -> 0 | V36: =+AA36-U36 -> 0 | W36: =+AB36-T36 -> 0 | Y36: =$AD$33*B36/$G$33 -> 0 | Z36: =Y36*I36 -> 0 | AA36: =+AF36-Z36 -> 0 | AB36: =+AG36-Y36 -> 0 | AD36: =$AD$33*G36/$G$33 -> 0
B37: 2172 | C37: Import Efill | E37: 6951.45 | F37: =$D$6/$E$6*E37 -> 9580.3582 | G37: 797.55 | H37: TON | I37: =F37/G37 -> 12.012235 | K37: =+J37*$I37 -> 0 | L37: =+Q37-K37 -> 0 | M37: =+R37-J37 -> 0 | P37: =O37*I37 -> 0 | Q37: =+V37-P37 -> 0 | R37: =+W37-O37 -> 0 | U37: =T37*D37 -> 0 | V37: =+AA37-U37 -> 0 | W37: =+AB37-T37 -> 0 | Y37: =$AD$33*B37/$G$33 -> 0 | Z37: =Y37*I37 -> 0 | AA37: =+AF37-Z37 -> 0 | AB37: =+AG37-Y37 -> 0 | AD37: =$AD$33*G37/$G$33 -> 0
B38: 2149 | C38: Import Trucking | E38: 6761.84 | F38: =$D$6/$E$6*E38 -> 9319.0413 | G38: 797.55 | H38: TON | I38: =F38/G38 -> 11.684586 | K38: =+J38*$I38 -> 0 | L38: =+Q38-K38 -> 0 | M38: =+R38-J38 -> 0 | P38: =O38*I38 -> 0 | Q38: =+V38-P38 -> 0 | R38: =+W38-O38 -> 0 | U38: =T38*D38 -> 0 | V38: =+AA38-U38 -> 0 | W38: =+AB38-T38 -> 0 | Y38: =$AD$33*B38/$G$33 -> 0 | Z38: =Y38*I38 -> 0 | AA38: =+AF38-Z38 -> 0 | AB38: =+AG38-Y38 -> 0 | AD38: =$AD$33*G38/$G$33 -> 0
B39: 2150 | C39: Export Trucking | E39: 6761.84 | F39: =$D$6/$E$6*E39 -> 9319.0413 | G39: 797.55 | H39: TON | I39: =F39/G39 -> 11.684586 | K39: =+J39*$I39 -> 0 | L39: =+Q39-K39 -> 0 | M39: =+R39-J39 -> 0 | P39: =O39*I39 -> 0 | Q39: =+V39-P39 -> 0 | R39: =+W39-O39 -> 0 | U39: =T39*D39 -> 0 | V39: =+AA39-U39 -> 0 | W39: =+AB39-T39 -> 0 | Y39: =$AD$33*B39/$G$33 -> 0 | Z39: =Y39*I39 -> 0 | AA39: =+AF39-Z39 -> 0 | AB39: =+AG39-Y39 -> 0 | AD39: =$AD$33*G39/$G$33 -> 0
B40: 2490 | C40: Dump Fees | E40: 2392.65 | F40: =$D$6/$E$6*E40 -> 3297.5054 | G40: 797.55 | H40: TON | I40: =F40/G40 -> 4.1345438 | K40: =+J40*$I40 -> 0 | L40: =+Q40-K40 -> 0 | M40: =+R40-J40 -> 0 | P40: =O40*I40 -> 0 | Q40: =+V40-P40 -> 0 | R40: =+W40-O40 -> 0 | U40: =T40*D40 -> 0 | V40: =+AA40-U40 -> 0 | W40: =+AB40-T40 -> 0 | Y40: =$AD$33*B40/$G$33 -> 0 | Z40: =Y40*I40 -> 0 | AA40: =+AF40-Z40 -> 0 | AB40: =+AG40-Y40 -> 0 | AD40: =$AD$33*G40/$G$33 -> 0
C41: Remove Pipe RCP 15" | E41: 32782 | F41: =$D$6/$E$6*E41 -> 45179.538 | G41: 1069 | H41: LF | I41: =F41/G41 -> 42.263366 | K41: =+J41*$I41 -> 0 | L41: =+Q41-K41 -> 45179.538 | M41: =+R41-J41 -> 1069 | N41: =100%-(L41/$F41) -> 0 | P41: =O41*I41 -> 0 | Q41: =+V41-P41 -> 45179.538 | R41: =+W41-O41 -> 1069 | S41: =100%-(Q41/$F41) -> 0 | U41: =T41*D41 -> 0 | V41: =+AA41-U41 -> 45179.538 | W41: =+AB41-T41 -> 1069 | X41: =100%-(V41/$F41) -> 0 | Z41: =Y41*I41 -> 0 | AA41: =+AF41-Z41 -> 45179.538 | AB41: =+AG41-Y41 -> 1069 | AC41: =100%-(AA41/$F41) -> 0 | AE41: =AD41*I41 -> 0 | AF41: =F41-AE41 -> 45179.538 | AG41: =G41-AD41 -> 1069 | AH41: =100%-(AF41/$F41) -> 0
B42: 2450 | C42: Remove Pipe | E42: 31104.19 | F42: =$D$6/$E$6*E42 -> 42867.212 | G42: 1069 | H42: LF | I42: =F42/G42 -> 40.100292 | K42: =+J42*$I42 -> 0 | L42: =+Q42-K42 -> 0 | M42: =+R42-J42 -> 0 | P42: =O42*I42 -> 0 | Q42: =+V42-P42 -> 0 | R42: =+W42-O42 -> 0 | U42: =T42*D42 -> 0 | V42: =+AA42-U42 -> 0 | W42: =+AB42-T42 -> 0 | Y42: =$AD$41*B42/$G$41 -> 0 | Z42: =Y42*I42 -> 0 | AA42: =+AF42-Z42 -> 0 | AB42: =+AG42-Y42 -> 0 | AD42: =$AD$41*G42/$G$41 -> 0
B43: 2490 | C43: Dump Fees | E43: 648.27 | F43: =$D$6/$E$6*E43 -> 893.43357 | G43: 67.88 | H43: TON | I43: =F43/G43 -> 13.161956 | K43: =+J43*$I43 -> 0 | L43: =+Q43-K43 -> 0 | M43: =+R43-J43 -> 0 | P43: =O43*I43 -> 0 | Q43: =+V43-P43 -> 0 | R43: =+W43-O43 -> 0 | U43: =T43*D43 -> 0 | V43: =+AA43-U43 -> 0 | W43: =+AB43-T43 -> 0 | Y43: =$AD$41*B43/$G$41 -> 0 | Z43: =Y43*I43 -> 0 | AA43: =+AF43-Z43 -> 0 | AB43: =+AG43-Y43 -> 0 | AD43: =$AD$41*G43/$G$41 -> 0
B44: 2150 | C44: Export Trucking | E44: 1029.54 | F44: =$D$6/$E$6*E44 -> 1418.8927 | G44: 67.88 | H44: TON | I44: =F44/G44 -> 20.902957 | K44: =+J44*$I44 -> 0 | L44: =+Q44-K44 -> 0 | M44: =+R44-J44 -> 0 | P44: =O44*I44 -> 0 | Q44: =+V44-P44 -> 0 | R44: =+W44-O44 -> 0 | U44: =T44*D44 -> 0 | V44: =+AA44-U44 -> 0 | W44: =+AB44-T44 -> 0 | Y44: =$AD$41*B44/$G$41 -> 0 | Z44: =Y44*I44 -> 0 | AA44: =+AF44-Z44 -> 0 | AB44: =+AG44-Y44 -> 0 | AD44: =$AD$41*G44/$G$41 -> 0
C45: Remove Light Pole/Base | E45: 2652.02 | F45: =$D$6/$E$6*E45 -> 3654.9643 | G45: 12 | H45: EACH | I45: =F45/G45 -> 304.58036 | J45: 6 | K45: =+J45*$I45 -> 1827.4821 | L45: =+Q45-K45 -> 1827.4821 | M45: =+R45-J45 -> 6 | N45: =100%-(L45/$F45) -> 0.5 | P45: =O45*I45 -> 0 | Q45: =+V45-P45 -> 3654.9643 | R45: =+W45-O45 -> 12 | S45: =100%-(Q45/$F45) -> 0 | U45: =T45*D45 -> 0 | V45: =+AA45-U45 -> 3654.9643 | W45: =+AB45-T45 -> 12 | X45: =100%-(V45/$F45) -> 0 | Z45: =Y45*I45 -> 0 | AA45: =+AF45-Z45 -> 3654.9643 | AB45: =+AG45-Y45 -> 12 | AC45: =100%-(AA45/$F45) -> 0 | AE45: =AD45*I45 -> 0 | AF45: =F45-AE45 -> 3654.9643 | AG45: =G45-AD45 -> 12 | AH45: =100%-(AF45/$F45) -> 0
B46: 2435 | C46: Remove Pole Base | E46: 2577.87 | F46: =$D$6/$E$6*E46 -> 3552.7722 | G46: 12 | H46: EACH | I46: =F46/G46 -> 296.06435 | K46: =+J46*$I46 -> 0 | L46: =+Q46-K46 -> 0 | M46: =+R46-J46 -> 0 | P46: =O46*I46 -> 0 | Q46: =+V46-P46 -> 0 | R46: =+W46-O46 -> 0 | U46: =T46*D46 -> 0 | V46: =+AA46-U46 -> 0 | W46: =+AB46-T46 -> 0 | Y46: =$AD$45*B46/$G$45 -> 0 | Z46: =Y46*I46 -> 0 | AA46: =+AF46-Z46 -> 0 | AB46: =+AG46-Y46 -> 0 | AD46: =$AD$45*G46/$G$45 -> 0
B47: 2490 | C47: Dump Fees | E47: 28.65 | F47: =$D$6/$E$6*E47 -> 39.484893 | G47: 3 | H47: TON | I47: =F47/G47 -> 13.161631 | K47: =+J47*$I47 -> 0 | L47: =+Q47-K47 -> 0 | M47: =+R47-J47 -> 0 | P47: =O47*I47 -> 0 | Q47: =+V47-P47 -> 0 | R47: =+W47-O47 -> 0 | U47: =T47*D47 -> 0 | V47: =+AA47-U47 -> 0 | W47: =+AB47-T47 -> 0 | Y47: =$AD$45*B47/$G$45 -> 0 | Z47: =Y47*I47 -> 0 | AA47: =+AF47-Z47 -> 0 | AB47: =+AG47-Y47 -> 0 | AD47: =$AD$45*G47/$G$45 -> 0
B48: 2150 | C48: Export Trucking | E48: 45.5 | F48: =$D$6/$E$6*E48 -> 62.707248 | G48: 3 | H48: TON | I48: =F48/G48 -> 20.902416 | K48: =+J48*$I48 -> 0 | L48: =+Q48-K48 -> 0 | M48: =+R48-J48 -> 0 | P48: =O48*I48 -> 0 | Q48: =+V48-P48 -> 0 | R48: =+W48-O48 -> 0 | U48: =T48*D48 -> 0 | V48: =+AA48-U48 -> 0 | W48: =+AB48-T48 -> 0 | Y48: =$AD$45*B48/$G$45 -> 0 | Z48: =Y48*I48 -> 0 | AA48: =+AF48-Z48 -> 0 | AB48: =+AG48-Y48 -> 0 | AD48: =$AD$45*G48/$G$45 -> 0
C49: Remove Fire Hydrant | E49: 2446.81 | F49: =$D$6/$E$6*E49 -> 3372.1477 | G49: 5 | H49: EACH | I49: =F49/G49 -> 674.42954 | J49: 1 | K49: =+J49*$I49 -> 674.42954 | L49: =+Q49-K49 -> 2697.7182 | M49: =+R49-J49 -> 4 | N49: =100%-(L49/$F49) -> 0.2 | P49: =O49*I49 -> 0 | Q49: =+V49-P49 -> 3372.1477 | R49: =+W49-O49 -> 5 | S49: =100%-(Q49/$F49) -> 0 | U49: =T49*D49 -> 0 | V49: =+AA49-U49 -> 3372.1477 | W49: =+AB49-T49 -> 5 | X49: =100%-(V49/$F49) -> 0 | Z49: =Y49*I49 -> 0 | AA49: =+AF49-Z49 -> 3372.1477 | AB49: =+AG49-Y49 -> 5 | AC49: =100%-(AA49/$F49) -> 0 | AE49: =AD49*I49 -> 0 | AF49: =F49-AE49 -> 3372.1477 | AG49: =G49-AD49 -> 5 | AH49: =100%-(AF49/$F49) -> 0
B50: 2400 | C50: Misc. Demolition | E50: 2418.18 | F50: =$D$6/$E$6*E50 -> 3332.6904 | G50: 1 | H50: LS | I50: =F50/G50 -> 3332.6904 | K50: =+J50*$I50 -> 0 | L50: =+Q50-K50 -> 0 | M50: =+R50-J50 -> 0 | P50: =O50*I50 -> 0 | Q50: =+V50-P50 -> 0 | R50: =+W50-O50 -> 0 | U50: =T50*D50 -> 0 | V50: =+AA50-U50 -> 0 | W50: =+AB50-T50 -> 0 | Y50: =$AD$49*B50/$G$49 -> 0 | Z50: =Y50*I50 -> 0 | AA50: =+AF50-Z50 -> 0 | AB50: =+AG50-Y50 -> 0 | AD50: =$AD$49*G50/$G$49 -> 0
B51: 2490 | C51: Dump Fees | E51: 25 | F51: =$D$6/$E$6*E51 -> 34.454532 | G51: 0.5 | H51: TON | I51: =F51/G51 -> 68.909064 | K51: =+J51*$I51 -> 0 | L51: =+Q51-K51 -> 0 | M51: =+R51-J51 -> 0 | P51: =O51*I51 -> 0 | Q51: =+V51-P51 -> 0 | R51: =+W51-O51 -> 0 | U51: =T51*D51 -> 0 | V51: =+AA51-U51 -> 0 | W51: =+AB51-T51 -> 0 | Y51: =$AD$49*B51/$G$49 -> 0 | Z51: =Y51*I51 -> 0 | AA51: =+AF51-Z51 -> 0 | AB51: =+AG51-Y51 -> 0 | AD51: =$AD$49*G51/$G$49 -> 0
B52: 2150 | C52: Export Trucking | E52: 3.63 | F52: =$D$6/$E$6*E52 -> 5.002798 | G52: 0.5 | H52: TON | I52: =F52/G52 -> 10.005596 | K52: =+J52*$I52 -> 0 | L52: =+Q52-K52 -> 0 | M52: =+R52-J52 -> 0 | P52: =O52*I52 -> 0 | Q52: =+V52-P52 -> 0 | R52: =+W52-O52 -> 0 | U52: =T52*D52 -> 0 | V52: =+AA52-U52 -> 0 | W52: =+AB52-T52 -> 0 | Y52: =$AD$49*B52/$G$49 -> 0 | Z52: =Y52*I52 -> 0 | AA52: =+AF52-Z52 -> 0 | AB52: =+AG52-Y52 -> 0 | AD52: =$AD$49*G52/$G$49 -> 0
C53: Remove Concrete Greast Trap | E53: 1253 | F53: =$D$6/$E$6*E53 -> 1726.8611 | G53: 1 | H53: EACH | I53: =F53/G53 -> 1726.8611 | K53: =+J53*$I53 -> 0 | L53: =+Q53-K53 -> 1726.8611 | M53: =+R53-J53 -> 1 | N53: =100%-(L53/$F53) -> 0 | P53: =O53*I53 -> 0 | Q53: =+V53-P53 -> 1726.8611 | R53: =+W53-O53 -> 1 | S53: =100%-(Q53/$F53) -> 0 | U53: =T53*D53 -> 0 | V53: =+AA53-U53 -> 1726.8611 | W53: =+AB53-T53 -> 1 | X53: =100%-(V53/$F53) -> 0 | Z53: =Y53*I53 -> 0 | AA53: =+AF53-Z53 -> 1726.8611 | AB53: =+AG53-Y53 -> 1 | AC53: =100%-(AA53/$F53) -> 0 | AE53: =AD53*I53 -> 0 | AF53: =F53-AE53 -> 1726.8611 | AG53: =G53-AD53 -> 1 | AH53: =100%-(AF53/$F53) -> 0
B54: 2456 | C54: Remove Catch Basin | E54: 808.75 | F54: =$D$6/$E$6*E54 -> 1114.6041 | G54: 1 | H54: EACH | I54: =F54/G54 -> 1114.6041 | K54: =+J54*$I54 -> 0 | L54: =+Q54-K54 -> 0 | M54: =+R54-J54 -> 0 | P54: =O54*I54 -> 0 | Q54: =+V54-P54 -> 0 | R54: =+W54-O54 -> 0 | U54: =T54*D54 -> 0 | V54: =+AA54-U54 -> 0 | W54: =+AB54-T54 -> 0 | Y54: =$AD$53*B54/$G$53 -> 0 | Z54: =Y54*I54 -> 0 | AA54: =+AF54-Z54 -> 0 | AB54: =+AG54-Y54 -> 0 | AD54: =$AD$53*G54/$G$53 -> 0
B55: 2490 | C55: Dump Fees | E55: 32.95 | F55: =$D$6/$E$6*E55 -> 45.411073 | G55: 5 | H55: TON | I55: =F55/G55 -> 9.0822146 | K55: =+J55*$I55 -> 0 | L55: =+Q55-K55 -> 0 | M55: =+R55-J55 -> 0 | P55: =O55*I55 -> 0 | Q55: =+V55-P55 -> 0 | R55: =+W55-O55 -> 0 | U55: =T55*D55 -> 0 | V55: =+AA55-U55 -> 0 | W55: =+AB55-T55 -> 0 | Y55: =$AD$53*B55/$G$53 -> 0 | Z55: =Y55*I55 -> 0 | AA55: =+AF55-Z55 -> 0 | AB55: =+AG55-Y55 -> 0 | AD55: =$AD$53*G55/$G$53 -> 0
B56: 2150 | C56: Export Trucking | E56: 75.83 | F56: =$D$6/$E$6*E56 -> 104.50749 | G56: 5 | H56: TON | I56: =F56/G56 -> 20.901497 | K56: =+J56*$I56 -> 0 | L56: =+Q56-K56 -> 0 | M56: =+R56-J56 -> 0 | P56: =O56*I56 -> 0 | Q56: =+V56-P56 -> 0 | R56: =+W56-O56 -> 0 | U56: =T56*D56 -> 0 | V56: =+AA56-U56 -> 0 | W56: =+AB56-T56 -> 0 | Y56: =$AD$53*B56/$G$53 -> 0 | Z56: =Y56*I56 -> 0 | AA56: =+AF56-Z56 -> 0 | AB56: =+AG56-Y56 -> 0 | AD56: =$AD$53*G56/$G$53 -> 0
B57: 2172 | C57: Import Efill | E57: 101.98 | F57: =$D$6/$E$6*E57 -> 140.54693 | G57: 11.7 | H57: TON | I57: =F57/G57 -> 12.012558 | K57: =+J57*$I57 -> 0 | L57: =+Q57-K57 -> 0 | M57: =+R57-J57 -> 0 | P57: =O57*I57 -> 0 | Q57: =+V57-P57 -> 0 | R57: =+W57-O57 -> 0 | U57: =T57*D57 -> 0 | V57: =+AA57-U57 -> 0 | W57: =+AB57-T57 -> 0 | Y57: =$AD$53*B57/$G$53 -> 0 | Z57: =Y57*I57 -> 0 | AA57: =+AF57-Z57 -> 0 | AB57: =+AG57-Y57 -> 0 | AD57: =$AD$53*G57/$G$53 -> 0
B58: 2149 | C58: Import Trucking | E58: 99.2 | F58: =$D$6/$E$6*E58 -> 136.71558 | G58: 11.7 | H58: TON | I58: =F58/G58 -> 11.685092 | K58: =+J58*$I58 -> 0 | L58: =+Q58-K58 -> 0 | M58: =+R58-J58 -> 0 | P58: =O58*I58 -> 0 | Q58: =+V58-P58 -> 0 | R58: =+W58-O58 -> 0 | U58: =T58*D58 -> 0 | V58: =+AA58-U58 -> 0 | W58: =+AB58-T58 -> 0 | Y58: =$AD$53*B58/$G$53 -> 0 | Z58: =Y58*I58 -> 0 | AA58: =+AF58-Z58 -> 0 | AB58: =+AG58-Y58 -> 0 | AD58: =$AD$53*G58/$G$53 -> 0
B59: 2150 | C59: Export Trucking | E59: 99.2 | F59: =$D$6/$E$6*E59 -> 136.71558 | G59: 11.7 | H59: TON | I59: =F59/G59 -> 11.685092 | K59: =+J59*$I59 -> 0 | L59: =+Q59-K59 -> 0 | M59: =+R59-J59 -> 0 | P59: =O59*I59 -> 0 | Q59: =+V59-P59 -> 0 | R59: =+W59-O59 -> 0 | U59: =T59*D59 -> 0 | V59: =+AA59-U59 -> 0 | W59: =+AB59-T59 -> 0 | Y59: =$AD$53*B59/$G$53 -> 0 | Z59: =Y59*I59 -> 0 | AA59: =+AF59-Z59 -> 0 | AB59: =+AG59-Y59 -> 0 | AD59: =$AD$53*G59/$G$53 -> 0
B60: 2490 | C60: Dump Fees | E60: 35.1 | F60: =$D$6/$E$6*E60 -> 48.374163 | G60: 11.7 | H60: TON | I60: =F60/G60 -> 4.1345438 | K60: =+J60*$I60 -> 0 | L60: =+Q60-K60 -> 0 | M60: =+R60-J60 -> 0 | P60: =O60*I60 -> 0 | Q60: =+V60-P60 -> 0 | R60: =+W60-O60 -> 0 | U60: =T60*D60 -> 0 | V60: =+AA60-U60 -> 0 | W60: =+AB60-T60 -> 0 | Y60: =$AD$53*B60/$G$53 -> 0 | Z60: =Y60*I60 -> 0 | AA60: =+AF60-Z60 -> 0 | AB60: =+AG60-Y60 -> 0 | AD60: =$AD$53*G60/$G$53 -> 0
C61: Remove Catch Basin 2020 | E61: 2601.67 | F61: =$D$6/$E$6*E61 -> 3585.5729 | G61: 7 | H61: EACH | I61: =F61/G61 -> 512.2247 | J61: 0 | K61: =+J61*$I61 -> 0 | L61: =+Q61-K61 -> 3585.5729 | M61: =+R61-J61 -> 7 | N61: =100%-(L61/$F61) -> 0 | O61: 0 | P61: =O61*I61 -> 0 | Q61: =+V61-P61 -> 3585.5729 | R61: =+W61-O61 -> 7 | S61: =100%-(Q61/$F61) -> 0 | T61: 0 | U61: =T61*D61 -> 0 | V61: =+AA61-U61 -> 3585.5729 | W61: =+AB61-T61 -> 7 | X61: =100%-(V61/$F61) -> 0 | Y61: 0 | Z61: =Y61*I61 -> 0 | AA61: =+AF61-Z61 -> 3585.5729 | AB61: =+AG61-Y61 -> 7 | AC61: =100%-(AA61/$F61) -> 0 | AD61: 0 | AE61: =AD61*I61 -> 0 | AF61: =F61-AE61 -> 3585.5729 | AG61: =G61-AD61 -> 7 | AH61: =100%-(AF61/$F61) -> 0
B62: 2456 | C62: Remove Catch Basin | E62: 2255.64 | F62: =$D$6/$E$6*E62 -> 3108.6808 | G62: 7 | H62: EACH | I62: =F62/G62 -> 444.09726 | K62: =+J62*$I62 -> 0 | L62: =+Q62-K62 -> 0 | M62: =+R62-J62 -> 0 | P62: =O62*I62 -> 0 | Q62: =+V62-P62 -> 0 | R62: =+W62-O62 -> 0 | U62: =T62*D62 -> 0 | V62: =+AA62-U62 -> 0 | W62: =+AB62-T62 -> 0 | Y62: =$AD$61*B62/$G$61 -> 0 | Z62: =Y62*I62 -> 0 | AA62: =+AF62-Z62 -> 0 | AB62: =+AG62-Y62 -> 0 | AD62: =$AD$61*G62/$G$61 -> 0
B63: 2490 | C63: Dump Fees | E63: 133.7 | F63: =$D$6/$E$6*E63 -> 184.26284 | G63: 7 | H63: TON | I63: =F63/G63 -> 26.323262 | K63: =+J63*$I63 -> 0 | L63: =+Q63-K63 -> 0 | M63: =+R63-J63 -> 0 | P63: =O63*I63 -> 0 | Q63: =+V63-P63 -> 0 | R63: =+W63-O63 -> 0 | U63: =T63*D63 -> 0 | V63: =+AA63-U63 -> 0 | W63: =+AB63-T63 -> 0 | Y63: =$AD$61*B63/$G$61 -> 0 | Z63: =Y63*I63 -> 0 | AA63: =+AF63-Z63 -> 0 | AB63: =+AG63-Y63 -> 0 | AD63: =$AD$61*G63/$G$61 -> 0
B64: 2150 | C64: Export Trucking | E64: 212.33 | F64: =$D$6/$E$6*E64 -> 292.62923 | G64: 7 | H64: TON | I64: =F64/G64 -> 41.804176 | K64: =+J64*$I64 -> 0 | L64: =+Q64-K64 -> 0 | M64: =+R64-J64 -> 0 | P64: =O64*I64 -> 0 | Q64: =+V64-P64 -> 0 | R64: =+W64-O64 -> 0 | U64: =T64*D64 -> 0 | V64: =+AA64-U64 -> 0 | W64: =+AB64-T64 -> 0 | Y64: =$AD$61*B64/$G$61 -> 0 | Z64: =Y64*I64 -> 0 | AA64: =+AF64-Z64 -> 0 | AB64: =+AG64-Y64 -> 0 | AD64: =$AD$61*G64/$G$61 -> 0
C65: Remove Manhole 60" | E65: 5217.8 | F65: =$D$6/$E$6*E65 -> 7191.0742 | G65: 5 | H65: EACH | I65: =F65/G65 -> 1438.2148 | K65: =+J65*$I65 -> 0 | L65: =+Q65-K65 -> 7191.0742 | M65: =+R65-J65 -> 5 | N65: =100%-(L65/$F65) -> 0 | P65: =O65*I65 -> 0 | Q65: =+V65-P65 -> 7191.0742 | R65: =+W65-O65 -> 5 | S65: =100%-(Q65/$F65) -> 0 | U65: =T65*D65 -> 0 | V65: =+AA65-U65 -> 7191.0742 | W65: =+AB65-T65 -> 5 | X65: =100%-(V65/$F65) -> 0 | Z65: =Y65*I65 -> 0 | AA65: =+AF65-Z65 -> 7191.0742 | AB65: =+AG65-Y65 -> 5 | AC65: =100%-(AA65/$F65) -> 0 | AE65: =AD65*I65 -> 0 | AF65: =F65-AE65 -> 7191.0742 | AG65: =G65-AD65 -> 5 | AH65: =100%-(AF65/$F65) -> 0
B66: 2455 | C66: Remove Manhole | E66: 4043.76 | F66: =$D$6/$E$6*E66 -> 5573.0343 | G66: 5 | H66: EACH | I66: =F66/G66 -> 1114.6069 | K66: =+J66*$I66 -> 0 | L66: =+Q66-K66 -> 0 | M66: =+R66-J66 -> 0 | P66: =O66*I66 -> 0 | Q66: =+V66-P66 -> 0 | R66: =+W66-O66 -> 0 | U66: =T66*D66 -> 0 | V66: =+AA66-U66 -> 0 | W66: =+AB66-T66 -> 0 | Y66: =$AD$65*B66/$G$65 -> 0 | Z66: =Y66*I66 -> 0 | AA66: =+AF66-Z66 -> 0 | AB66: =+AG66-Y66 -> 0 | AD66: =$AD$65*G66/$G$65 -> 0
B67: 2490 | C67: Dump Fees | E67: 453.63 | F67: =$D$6/$E$6*E67 -> 625.18437 | G67: 47.5 | H67: TON | I67: =F67/G67 -> 13.161776 | K67: =+J67*$I67 -> 0 | L67: =+Q67-K67 -> 0 | M67: =+R67-J67 -> 0 | P67: =O67*I67 -> 0 | Q67: =+V67-P67 -> 0 | R67: =+W67-O67 -> 0 | U67: =T67*D67 -> 0 | V67: =+AA67-U67 -> 0 | W67: =+AB67-T67 -> 0 | Y67: =$AD$65*B67/$G$65 -> 0 | Z67: =Y67*I67 -> 0 | AA67: =+AF67-Z67 -> 0 | AB67: =+AG67-Y67 -> 0 | AD67: =$AD$65*G67/$G$65 -> 0
B68: 2150 | C68: Export Trucking | E68: 720.42 | F68: =$D$6/$E$6*E68 -> 992.86935 | G68: 47.5 | H68: TON | I68: =F68/G68 -> 20.902513 | K68: =+J68*$I68 -> 0 | L68: =+Q68-K68 -> 0 | M68: =+R68-J68 -> 0 | P68: =O68*I68 -> 0 | Q68: =+V68-P68 -> 0 | R68: =+W68-O68 -> 0 | U68: =T68*D68 -> 0 | V68: =+AA68-U68 -> 0 | W68: =+AB68-T68 -> 0 | Y68: =$AD$65*B68/$G$65 -> 0 | Z68: =Y68*I68 -> 0 | AA68: =+AF68-Z68 -> 0 | AB68: =+AG68-Y68 -> 0 | AD68: =$AD$65*G68/$G$65 -> 0
C69: Remove Water Meter 2020 | E69: 1298.54 | F69: =$D$6/$E$6*E69 -> 1789.6235 | G69: 2 | H69: EACH | I69: =F69/G69 -> 894.81175 | K69: =+J69*$I69 -> 0 | L69: =+Q69-K69 -> 1789.6235 | M69: =+R69-J69 -> 2 | N69: =100%-(L69/$F69) -> 0 | P69: =O69*I69 -> 0 | Q69: =+V69-P69 -> 1789.6235 | R69: =+W69-O69 -> 2 | S69: =100%-(Q69/$F69) -> 0 | U69: =T69*D69 -> 0 | V69: =+AA69-U69 -> 1789.6235 | W69: =+AB69-T69 -> 2 | X69: =100%-(V69/$F69) -> 0 | Z69: =Y69*I69 -> 0 | AA69: =+AF69-Z69 -> 1789.6235 | AB69: =+AG69-Y69 -> 2 | AC69: =100%-(AA69/$F69) -> 0 | AE69: =AD69*I69 -> 0 | AF69: =F69-AE69 -> 1789.6235 | AG69: =G69-AD69 -> 2 | AH69: =100%-(AF69/$F69) -> 0
B70: 2400 | C70: Misc. Demolition | E70: 725.45 | F70: =$D$6/$E$6*E70 -> 999.8016 | G70: 1 | H70: LS | I70: =F70/G70 -> 999.8016 | K70: =+J70*$I70 -> 0 | L70: =+Q70-K70 -> 0 | M70: =+R70-J70 -> 0 | P70: =O70*I70 -> 0 | Q70: =+V70-P70 -> 0 | R70: =+W70-O70 -> 0 | U70: =T70*D70 -> 0 | V70: =+AA70-U70 -> 0 | W70: =+AB70-T70 -> 0 | Y70: =$AD$69*B70/$G$69 -> 0 | Z70: =Y70*I70 -> 0 | AA70: =+AF70-Z70 -> 0 | AB70: =+AG70-Y70 -> 0 | AD70: =$AD$69*G70/$G$69 -> 0
B71: 2490 | C71: Dump Fees | E71: 200 | F71: =$D$6/$E$6*E71 -> 275.63625 | G71: 4 | H71: TON | I71: =F71/G71 -> 68.909064 | K71: =+J71*$I71 -> 0 | L71: =+Q71-K71 -> 0 | M71: =+R71-J71 -> 0 | P71: =O71*I71 -> 0 | Q71: =+V71-P71 -> 0 | R71: =+W71-O71 -> 0 | U71: =T71*D71 -> 0 | V71: =+AA71-U71 -> 0 | W71: =+AB71-T71 -> 0 | Y71: =$AD$69*B71/$G$69 -> 0 | Z71: =Y71*I71 -> 0 | AA71: =+AF71-Z71 -> 0 | AB71: =+AG71-Y71 -> 0 | AD71: =$AD$69*G71/$G$69 -> 0
B72: 2150 | C72: Export Trucking | E72: 29.01 | F72: =$D$6/$E$6*E72 -> 39.981039 | G72: 4 | H72: TON | I72: =F72/G72 -> 9.9952597 | K72: =+J72*$I72 -> 0 | L72: =+Q72-K72 -> 0 | M72: =+R72-J72 -> 0 | P72: =O72*I72 -> 0 | Q72: =+V72-P72 -> 0 | R72: =+W72-O72 -> 0 | U72: =T72*D72 -> 0 | V72: =+AA72-U72 -> 0 | W72: =+AB72-T72 -> 0 | Y72: =$AD$69*B72/$G$69 -> 0 | Z72: =Y72*I72 -> 0 | AA72: =+AF72-Z72 -> 0 | AB72: =+AG72-Y72 -> 0 | AD72: =$AD$69*G72/$G$69 -> 0
B73: 2172 | C73: Import Efill | E73: 104.59 | F73: =$D$6/$E$6*E73 -> 144.14398 | G73: 12 | H73: TON | I73: =F73/G73 -> 12.011998 | K73: =+J73*$I73 -> 0 | L73: =+Q73-K73 -> 0 | M73: =+R73-J73 -> 0 | P73: =O73*I73 -> 0 | Q73: =+V73-P73 -> 0 | R73: =+W73-O73 -> 0 | U73: =T73*D73 -> 0 | V73: =+AA73-U73 -> 0 | W73: =+AB73-T73 -> 0 | Y73: =$AD$69*B73/$G$69 -> 0 | Z73: =Y73*I73 -> 0 | AA73: =+AF73-Z73 -> 0 | AB73: =+AG73-Y73 -> 0 | AD73: =$AD$69*G73/$G$69 -> 0
B74: 2149 | C74: Import Trucking | E74: 101.74 | F74: =$D$6/$E$6*E74 -> 140.21616 | G74: 12 | H74: TON | I74: =F74/G74 -> 11.68468 | K74: =+J74*$I74 -> 0 | L74: =+Q74-K74 -> 0 | M74: =+R74-J74 -> 0 | P74: =O74*I74 -> 0 | Q74: =+V74-P74 -> 0 | R74: =+W74-O74 -> 0 | U74: =T74*D74 -> 0 | V74: =+AA74-U74 -> 0 | W74: =+AB74-T74 -> 0 | Y74: =$AD$69*B74/$G$69 -> 0 | Z74: =Y74*I74 -> 0 | AA74: =+AF74-Z74 -> 0 | AB74: =+AG74-Y74 -> 0 | AD74: =$AD$69*G74/$G$69 -> 0
B75: 2150 | C75: Export Trucking | E75: 101.74 | F75: =$D$6/$E$6*E75 -> 140.21616 | G75: 12 | H75: TON | I75: =F75/G75 -> 11.68468 | K75: =+J75*$I75 -> 0 | L75: =+Q75-K75 -> 0 | M75: =+R75-J75 -> 0 | P75: =O75*I75 -> 0 | Q75: =+V75-P75 -> 0 | R75: =+W75-O75 -> 0 | U75: =T75*D75 -> 0 | V75: =+AA75-U75 -> 0 | W75: =+AB75-T75 -> 0 | Y75: =$AD$69*B75/$G$69 -> 0 | Z75: =Y75*I75 -> 0 | AA75: =+AF75-Z75 -> 0 | AB75: =+AG75-Y75 -> 0 | AD75: =$AD$69*G75/$G$69 -> 0
B76: 2490 | C76: Dump Fees | E76: 36 | F76: =$D$6/$E$6*E76 -> 49.614526 | G76: 12 | H76: TON | I76: =F76/G76 -> 4.1345438 | K76: =+J76*$I76 -> 0 | L76: =+Q76-K76 -> 0 | M76: =+R76-J76 -> 0 | P76: =O76*I76 -> 0 | Q76: =+V76-P76 -> 0 | R76: =+W76-O76 -> 0 | U76: =T76*D76 -> 0 | V76: =+AA76-U76 -> 0 | W76: =+AB76-T76 -> 0 | Y76: =$AD$69*B76/$G$69 -> 0 | Z76: =Y76*I76 -> 0 | AA76: =+AF76-Z76 -> 0 | AB76: =+AG76-Y76 -> 0 | AD76: =$AD$69*G76/$G$69 -> 0
C77: Remove Basketball Standard | E77: 991.42 | F77: =$D$6/$E$6*E77 -> 1366.3565 | G77: 4 | H77: EACH | I77: =F77/G77 -> 341.58912 | J77: 4 | K77: =+J77*$I77 -> 1366.3565 | L77: =+Q77-K77 -> 0 | M77: =+R77-J77 -> 0 | N77: =100%-(L77/$F77) -> 1 | P77: =O77*I77 -> 0 | Q77: =+V77-P77 -> 1366.3565 | R77: =+W77-O77 -> 4 | S77: =100%-(Q77/$F77) -> 0 | U77: =T77*D77 -> 0 | V77: =+AA77-U77 -> 1366.3565 | W77: =+AB77-T77 -> 4 | X77: =100%-(V77/$F77) -> 0 | Z77: =Y77*I77 -> 0 | AA77: =+AF77-Z77 -> 1366.3565 | AB77: =+AG77-Y77 -> 4 | AC77: =100%-(AA77/$F77) -> 0 | AE77: =AD77*I77 -> 0 | AF77: =F77-AE77 -> 1366.3565 | AG77: =G77-AD77 -> 4 | AH77: =100%-(AF77/$F77) -> 0
B78: 2435 | C78: Remove Pole Base | E78: 966.7 | F78: =$D$6/$E$6*E78 -> 1332.2878 | G78: 4 | H78: EACH | I78: =F78/G78 -> 333.07196 | K78: =+J78*$I78 -> 0 | L78: =+Q78-K78 -> 0 | M78: =+R78-J78 -> 0 | P78: =O78*I78 -> 0 | Q78: =+V78-P78 -> 0 | R78: =+W78-O78 -> 0 | U78: =T78*D78 -> 0 | V78: =+AA78-U78 -> 0 | W78: =+AB78-T78 -> 0 | Y78: =$AD$77*B78/$G$77 -> 0 | Z78: =Y78*I78 -> 0 | AA78: =+AF78-Z78 -> 0 | AB78: =+AG78-Y78 -> 0 | AD78: =$AD$77*G78/$G$77 -> 0
B79: 2490 | C79: Dump Fees | E79: 9.55 | F79: =$D$6/$E$6*E79 -> 13.161631 | G79: 1 | H79: TON | I79: =F79/G79 -> 13.161631 | K79: =+J79*$I79 -> 0 | L79: =+Q79-K79 -> 0 | M79: =+R79-J79 -> 0 | P79: =O79*I79 -> 0 | Q79: =+V79-P79 -> 0 | R79: =+W79-O79 -> 0 | U79: =T79*D79 -> 0 | V79: =+AA79-U79 -> 0 | W79: =+AB79-T79 -> 0 | Y79: =$AD$77*B79/$G$77 -> 0 | Z79: =Y79*I79 -> 0 | AA79: =+AF79-Z79 -> 0 | AB79: =+AG79-Y79 -> 0 | AD79: =$AD$77*G79/$G$77 -> 0
B80: 2150 | C80: Export Trucking | E80: 15.17 | F80: =$D$6/$E$6*E80 -> 20.90701 | G80: 1 | H80: TON | I80: =F80/G80 -> 20.90701 | K80: =+J80*$I80 -> 0 | L80: =+Q80-K80 -> 0 | M80: =+R80-J80 -> 0 | P80: =O80*I80 -> 0 | Q80: =+V80-P80 -> 0 | R80: =+W80-O80 -> 0 | U80: =T80*D80 -> 0 | V80: =+AA80-U80 -> 0 | W80: =+AB80-T80 -> 0 | Y80: =$AD$77*B80/$G$77 -> 0 | Z80: =Y80*I80 -> 0 | AA80: =+AF80-Z80 -> 0 | AB80: =+AG80-Y80 -> 0 | AD80: =$AD$77*G80/$G$77 -> 0
C81: Demo Bollard | E81: 4941.05 | F81: =$D$6/$E$6*E81 -> 6809.6626 | G81: 32 | H81: EACH | I81: =F81/G81 -> 212.80196 | J81: 10 | K81: =+J81*$I81 -> 2128.0196 | L81: =+Q81-K81 -> 4681.643 | M81: =+R81-J81 -> 22 | N81: =100%-(L81/$F81) -> 0.3125 | P81: =O81*I81 -> 0 | Q81: =+V81-P81 -> 6809.6626 | R81: =+W81-O81 -> 32 | S81: =100%-(Q81/$F81) -> 0 | U81: =T81*D81 -> 0 | V81: =+AA81-U81 -> 6809.6626 | W81: =+AB81-T81 -> 32 | X81: =100%-(V81/$F81) -> 0 | Z81: =Y81*I81 -> 0 | AA81: =+AF81-Z81 -> 6809.6626 | AB81: =+AG81-Y81 -> 32 | AC81: =100%-(AA81/$F81) -> 0 | AE81: =AD81*I81 -> 0 | AF81: =F81-AE81 -> 6809.6626 | AG81: =G81-AD81 -> 32 | AH81: =100%-(AF81/$F81) -> 0
B82: 2400 | C82: Misc. Demolition | E82: 4833.51 | F82: =$D$6/$E$6*E82 -> 6661.453 | G82: 1 | H82: LS | I82: =F82/G82 -> 6661.453 | L82: =+Q82-K82 -> 0 | Q82: =+V82-P82 -> 0 | V82: =+AA82-U82 -> 0 | Y82: =$AD$81*B82/$G$81 -> 0 | AA82: =+AF82-Z82 -> 0 | AD82: =$AD$81*G82/$G$81 -> 0
B83: 2490 | C83: Dump Fees | E83: 61.12 | F83: =$D$6/$E$6*E83 -> 84.234439 | G83: 6.4 | H83: TON | I83: =F83/G83 -> 13.161631 | L83: =+Q83-K83 -> 0 | Q83: =+V83-P83 -> 0 | V83: =+AA83-U83 -> 0 | Y83: =$AD$81*B83/$G$81 -> 0 | AA83: =+AF83-Z83 -> 0 | AD83: =$AD$81*G83/$G$81 -> 0
B84: 2150 | C84: Export Trucking | E84: 46.42 | F84: =$D$6/$E$6*E84 -> 63.975175 | G84: 6.4 | H84: TON | I84: =F84/G84 -> 9.996121 | L84: =+Q84-K84 -> 0 | Q84: =+V84-P84 -> 0 | V84: =+AA84-U84 -> 0 | Y84: =$AD$81*B84/$G$81 -> 0 | AA84: =+AF84-Z84 -> 0 | AD84: =$AD$81*G84/$G$81 -> 0
A85: 3 | C85: Site Earthwork | D85: =_xlfn.XLOOKUP(A85,SOV!$A$9:$A$27,SOV!$C$9:$C$27) -> 1267100 | E85: 912203.67 | F85: =+F86+F88+F90+F94+F97+F99+F101+F104 -> 1267100 | K85: =+K86+K88+K90+K94+K97+K99+K101+K104 -> 0 | L85: =+Q85-K85 -> 757247.45 | P85: =+P86+P88+P90+P94+P97+P99+P101+P104 -> 30233.319 | Q85: =+V85-P85 -> 757247.45 | U85: =+U86+U88+U90+U94+U97+U99+U101+U104 -> 88343.916 | V85: =+AA85-U85 -> 787480.77 | Z85: =SUM(Z86:Z106) -> 28441.676 | AA85: =+AF85-Z85 -> 875824.68 | AE85: =SUM(AE86:AE106) -> 362833.63 | AF85: =SUM(AF86:AF106) -> 904266.36
C86: Strip & Stockpile Topsoil Onsite Phase 1 | E86: 16412.94 | F86: =$D$85/$E$85*E86 -> 22798.457 | G86: 4500 | H86: CY | I86: =F86/G86 -> 5.0663238 | K86: =+J86*$I86 -> 0 | L86: =+Q86-K86 -> 0 | M86: =+R86-J86 -> 0 | N86: =100%-(L86/$F86) -> 1 | P86: =+O86*$I86 -> 0 | Q86: =+V86-P86 -> 0 | R86: =+W86-O86 -> 0 | S86: =100%-(Q86/$F86) -> 1 | U86: =+T86*$I86 -> 0 | V86: =+AA86-U86 -> 0 | W86: =+AB86-T86 -> 0 | X86: =100%-(V86/$F86) -> 1 | Z86: =Y86*I86 -> 0 | AA86: =+AF86-Z86 -> 0 | AB86: =+AG86-Y86 -> 0 | AC86: =100%-(AA86/$F86) -> 1 | AD86: 4500 | AE86: =AD86*I86 -> 22798.457 | AF86: =F86-AE86 -> 0 | AG86: =G86-AD86 -> 0 | AH86: =100%-(AF86/$F86) -> 1
B87: 2120 | C87: Strip Topsoil | E87: 16412.94 | F87: =$D$85/$E$85*E87 -> 22798.457 | G87: 4500 | H87: CY | I87: =F87/G87 -> 5.0663238 | K87: =+J87*$I87 -> 0 | L87: =+Q87-K87 -> 0 | M87: =+R87-J87 -> 0 | P87: =+O87*$I87 -> 0 | Q87: =+V87-P87 -> 0 | R87: =+W87-O87 -> 0 | U87: =+T87*$I87 -> 0 | V87: =+AA87-U87 -> 0 | W87: =+AB87-T87 -> 0 | Z87: =Y87*I87 -> 0 | AA87: =+AF87-Z87 -> 0 | AB87: =+AG87-Y87 -> 0 | AD87: =AD86 -> 4500
C88: KSC Cut To Fill (D8/D6/621/563) Phase 1 | E88: 29598.11 | F88: =$D$85/$E$85*E88 -> 41113.368 | G88: 3033 | H88: CY | I88: =F88/G88 -> 13.555347 | K88: =+J88*$I88 -> 0 | L88: =+Q88-K88 -> 0 | M88: =+R88-J88 -> 0 | N88: =100%-(L88/$F88) -> 1 | P88: =+O88*$I88 -> 0 | Q88: =+V88-P88 -> 0 | R88: =+W88-O88 -> 0 | S88: =100%-(Q88/$F88) -> 1 | T88: 533 | U88: =+T88*$I88 -> 7225 | V88: =+AA88-U88 -> 0 | W88: =+AB88-T88 -> 0 | X88: =100%-(V88/$F88) -> 1 | Y88: 500 | Z88: =Y88*I88 -> 6777.6736 | AA88: =+AF88-Z88 -> 7225 | AB88: =+AG88-Y88 -> 533 | AC88: =100%-(AA88/$F88) -> 0.8242664 | AD88: 2000 | AE88: =AD88*I88 -> 27110.694 | AF88: =F88-AE88 -> 14002.674 | AG88: =+G88-AD88 -> 1033 | AH88: =100%-(AF88/$F88) -> 0.65941312
B89: 2130 | C89: Cut To Fill | E89: 29598.11 | F89: =$D$85/$E$85*E89 -> 41113.368 | G89: 3033 | H89: CY | I89: =F89/G89 -> 13.555347 | K89: =+J89*$I89 -> 0 | L89: =+Q89-K89 -> 0 | M89: =+R89-J89 -> 0 | P89: =+O89*$I89 -> 0 | Q89: =+V89-P89 -> 0 | R89: =+W89-O89 -> 0 | U89: =+T89*$I89 -> 0 | V89: =+AA89-U89 -> 0 | W89: =+AB89-T89 -> 0 | Z89: =Y89*I89 -> 0 | AA89: =+AF89-Z89 -> 0 | AB89: =+AG89-Y89 -> 0 | AD89: =AD88 -> 2000
C90: Import A1A Compacted CY Phase 1 | E90: 336393.34 | F90: =$D$85/$E$85*E90 -> 467268.46 | G90: 9706 | H90: CY | I90: =F90/G90 -> 48.142227 | K90: =+J90*$I90 -> 0 | L90: =+Q90-K90 -> 30233.319 | M90: =+R90-J90 -> 628 | N90: =100%-(L90/$F90) -> 0.93529775 | O90: 628 | P90: =+O90*$I90 -> 30233.319 | Q90: =+V90-P90 -> 30233.319 | R90: =+W90-O90 -> 628 | S90: =100%-(Q90/$F90) -> 0.93529775 | T90: 1500 | U90: =+T90*$I90 -> 72213.341 | V90: =+AA90-U90 -> 60466.637 | W90: =+AB90-T90 -> 1256 | X90: =100%-(V90/$F90) -> 0.87059551 | Y90: 450 | Z90: =Y90*I90 -> 21664.002 | AA90: =+AF90-Z90 -> 132679.98 | AB90: =+AG90-Y90 -> 2756 | AC90: =100%-(AA90/$F90) -> 0.71605193 | AD90: 6500 | AE90: =AD90*I90 -> 312924.48 | AF90: =F90-AE90 -> 154343.98 | AG90: =G90-AD90 -> 3206 | AH90: =100%-(AF90/$F90) -> 0.66968885
B91: 2129 | C91: Place Fill | E91: 35995.8 | F91: =$D$85/$E$85*E91 -> 50000.104 | G91: 17470.8 | H91: TON | I91: =F91/G91 -> 2.8619241 | K91: =+J91*$I91 -> 0 | L91: =+Q91-K91 -> 0 | M91: =+R91-J91 -> 0 | P91: =+O91*$I91 -> 0 | Q91: =+V91-P91 -> 0 | R91: =+W91-O91 -> 0 | U91: =+T91*$I91 -> 0 | V91: =+AA91-U91 -> 0 | W91: =+AB91-T91 -> 0 | Z91: =Y91*I91 -> 0 | AA91: =+AF91-Z91 -> 0 | AB91: =+AG91-Y91 -> 0 | AD91: 11700
B92: 2172 | C92: Import Efill | E92: 152275.55 | F92: =$D$85/$E$85*E92 -> 211518.94 | G92: 17470.8 | H92: TON | I92: =F92/G92 -> 12.106998 | K92: =+J92*$I92 -> 0 | L92: =+Q92-K92 -> 0 | M92: =+R92-J92 -> 0 | P92: =+O92*$I92 -> 0 | Q92: =+V92-P92 -> 0 | R92: =+W92-O92 -> 0 | U92: =+T92*$I92 -> 0 | V92: =+AA92-U92 -> 0 | W92: =+AB92-T92 -> 0 | Z92: =Y92*I92 -> 0 | AA92: =+AF92-Z92 -> 0 | AB92: =+AG92-Y92 -> 0 | AD92: 11700
B93: 2149 | C93: Import Trucking | E93: 148122 | F93: =$D$85/$E$85*E93 -> 205749.43 | G93: 17470.8 | H93: TON | I93: =F93/G93 -> 11.776761 | K93: =+J93*$I93 -> 0 | L93: =+Q93-K93 -> 0 | M93: =+R93-J93 -> 0 | P93: =+O93*$I93 -> 0 | Q93: =+V93-P93 -> 0 | R93: =+W93-O93 -> 0 | U93: =+T93*$I93 -> 0 | V93: =+AA93-U93 -> 0 | W93: =+AB93-T93 -> 0 | Z93: =Y93*I93 -> 0 | AA93: =+AF93-Z93 -> 0 | AB93: =+AG93-Y93 -> 0 | AD93: 11700
C94: Fine Grade Roadway (140/563) Phase 1 | E94: 28753.24 | F94: =$D$85/$E$85*E94 -> 39939.798 | G94: 309531 | H94: SF | I94: =F94/G94 -> 0.12903327 | K94: =+J94*$I94 -> 0 | L94: =+Q94-K94 -> 39939.798 | M94: =+R94-J94 -> 309531 | N94: =100%-(L94/$F94) -> 0 | P94: =+O94*$I94 -> 0 | Q94: =+V94-P94 -> 39939.798 | R94: =+W94-O94 -> 309531 | S94: =100%-(Q94/$F94) -> 0 | U94: =+T94*$I94 -> 0 | V94: =+AA94-U94 -> 39939.798 | W94: =+AB94-T94 -> 309531 | X94: =100%-(V94/$F94) -> 0 | Z94: =Y94*I94 -> 0 | AA94: =+AF94-Z94 -> 39939.798 | AB94: =+AG94-Y94 -> 309531 | AC94: =100%-(AA94/$F94) -> 0 | AE94: =AD94*I94 -> 0 | AF94: =F94-AE94 -> 39939.798 | AG94: =G94-AD94 -> 309531 | AH94: =100%-(AF94/$F94) -> 0
B95: 2135 | C95: Fine Grade | E95: 28103.22 | F95: =$D$85/$E$85*E95 -> 39036.885 | G95: 309531 | H95: SF | I95: =F95/G95 -> 0.12611624 | J95: =J$94*$G95/$G$94 -> 0 | K95: =+J95*$I95 -> 0 | L95: =+Q95-K95 -> 0 | M95: =+R95-J95 -> 0 | O95: =O$94*$G95/$G$94 -> 0 | P95: =+O95*$I95 -> 0 | Q95: =+V95-P95 -> 0 | R95: =+W95-O95 -> 0 | T95: =T$94*G95/$G$94 -> 0 | U95: =+T95*$I95 -> 0 | V95: =+AA95-U95 -> 0 | W95: =+AB95-T95 -> 0 | Y95: =$AD$94*B95/$G$94 -> 0 | Z95: =Y95*I95 -> 0 | AA95: =+AF95-Z95 -> 0 | AB95: =+AG95-Y95 -> 0 | AD95: =$AD$94*G95/$G$94 -> 0
B96: 1410 | C96: Construction Water | E96: 650.02 | F96: =$D$85/$E$85*E96 -> 902.91277 | G96: 185.72 | H96: MGAL | I96: =F96/G96 -> 4.8616884 | J96: =J$94*$G96/$G$94 -> 0 | K96: =+J96*$I96 -> 0 | L96: =+Q96-K96 -> 0 | M96: =+R96-J96 -> 0 | O96: =O$94*$G96/$G$94 -> 0 | P96: =+O96*$I96 -> 0 | Q96: =+V96-P96 -> 0 | R96: =+W96-O96 -> 0 | T96: =T$94*G96/$G$94 -> 0 | U96: =+T96*$I96 -> 0 | V96: =+AA96-U96 -> 0 | W96: =+AB96-T96 -> 0 | Y96: =$AD$94*B96/$G$94 -> 0 | Z96: =Y96*I96 -> 0 | AA96: =+AF96-Z96 -> 0 | AB96: =+AG96-Y96 -> 0 | AD96: =$AD$94*G96/$G$94 -> 0
C97: KSC Cut To Fill (D8/D6/621/563) Phase 2 | E97: 14824.06 | F97: =$D$85/$E$85*E97 -> 20591.417 | G97: 1733 | H97: CY | I97: =F97/G97 -> 11.881949 | K97: =+J97*$I97 -> 0 | L97: =+Q97-K97 -> 20591.417 | M97: =+R97-J97 -> 1733 | N97: =100%-(L97/$F97) -> 0 | P97: =+O97*$I97 -> 0 | Q97: =+V97-P97 -> 20591.417 | R97: =+W97-O97 -> 1733 | S97: =100%-(Q97/$F97) -> 0 | U97: =+T97*$I97 -> 0 | V97: =+AA97-U97 -> 20591.417 | W97: =+AB97-T97 -> 1733 | X97: =100%-(V97/$F97) -> 0 | Z97: =Y97*I97 -> 0 | AA97: =+AF97-Z97 -> 20591.417 | AB97: =+AG97-Y97 -> 1733 | AC97: =100%-(AA97/$F97) -> 0 | AE97: =AD97*I97 -> 0 | AF97: =F97-AE97 -> 20591.417 | AG97: =G97-AD97 -> 1733 | AH97: =100%-(AF97/$F97) -> 0
B98: 2130 | C98: Cut To Fill | E98: 14824.06 | F98: =$D$85/$E$85*E98 -> 20591.417 | G98: 1733 | H98: CY | I98: =F98/G98 -> 11.881949 | J98: =J97 -> 0 | K98: =+J98*$I98 -> 0 | L98: =+Q98-K98 -> 0 | M98: =+R98-J98 -> 0 | O98: =O97 -> 0 | P98: =+O98*$I98 -> 0 | Q98: =+V98-P98 -> 0 | R98: =+W98-O98 -> 0 | T98: =T97 -> 0 | U98: =+T98*$I98 -> 0 | V98: =+AA98-U98 -> 0 | W98: =+AB98-T98 -> 0 | Y98: =Y97 -> 0 | Z98: =Y98*I98 -> 0 | AA98: =+AF98-Z98 -> 0 | AB98: =+AG98-Y98 -> 0 | AD98: =AD97 -> 0
C99: KSC Cut To Stockpile Phase 2 | E99: 143821.35 | F99: =$D$85/$E$85*E99 -> 199775.6 | G99: 18818 | H99: CY | I99: =F99/G99 -> 10.616197 | K99: =+J99*$I99 -> 0 | L99: =+Q99-K99 -> 199775.6 | M99: =+R99-J99 -> 18818 | N99: =100%-(L99/$F99) -> 0 | P99: =+O99*$I99 -> 0 | Q99: =+V99-P99 -> 199775.6 | R99: =+W99-O99 -> 18818 | S99: =100%-(Q99/$F99) -> 0 | U99: =+T99*$I99 -> 0 | V99: =+AA99-U99 -> 199775.6 | W99: =+AB99-T99 -> 18818 | X99: =100%-(V99/$F99) -> 0 | Z99: =Y99*I99 -> 0 | AA99: =+AF99-Z99 -> 199775.6 | AB99: =+AG99-Y99 -> 18818 | AC99: =100%-(AA99/$F99) -> 0 | AE99: =AD99*I99 -> 0 | AF99: =F99-AE99 -> 199775.6 | AG99: =G99-AD99 -> 18818 | AH99: =100%-(AF99/$F99) -> 0
B100: 2130 | C100: Cut To Fill | E100: 143821.35 | F100: =$D$85/$E$85*E100 -> 199775.6 | G100: 18818 | H100: CY | I100: =F100/G100 -> 10.616197 | K100: =+J100*$I100 -> 0 | L100: =+Q100-K100 -> 0 | M100: =+R100-J100 -> 0 | P100: =+O100*$I100 -> 0 | Q100: =+V100-P100 -> 0 | R100: =+W100-O100 -> 0 | U100: =+T100*$I100 -> 0 | V100: =+AA100-U100 -> 0 | W100: =+AB100-T100 -> 0 | Z100: =Y100*I100 -> 0 | AA100: =+AF100-Z100 -> 0 | AB100: =+AG100-Y100 -> 0
...

Sheet Sheet2

Sheet Sheet1
A1: Item # | B1: Job Cost ID | C1: Description | E1: Total Direct Cost | F1: Quantity | G1: UM | H1: Total Bid Price | I1: Total Plug | J1: Total Labor | K1: Total Equip. | L1: Total Material | M1: Total Subcontracted | N1: Total Trucking
A2: 1 | C2: Temporary Erosion & Sediment Control | E2: 29138.084 | F2: 1 | G2: LS | H2: 40400 | I2: 0 | J2: 9053.2677 | K2: 5871.251 | L2: 9278.9553 | M2: 0 | N2: 4934.6105
B3: 2100 | C3: SWPPP | E3: 29138.084 | F3: 1 | G3: LS | I3: 0 | J3: 9053.2677 | K3: 5871.251 | L3: 9278.9553 | M3: 0 | N3: 4934.6105
A4: 2 | C4: Site Demolition | E4: 422513.36 | F4: 1 | G4: LS | H4: 582300 | I4: 0 | J4: 124610.32 | K4: 152212.82 | L4: 44681.631 | M4: 16900 | N4: 84108.58
B5: 2402 | C5: Tree Removal | E5: 16900 | F5: 1 | G5: LS | I5: 0 | J5: 0 | K5: 0 | L5: 0 | M5: 16900 | N5: 0
C6: Remove Concrete Flatwork 04" | E6: 16075.116 | F6: 17303 | G6: SF | I6: 0 | J6: 3351.4377 | K6: 3312.2886 | L6: 2850.6692 | M6: 0 | N6: 6560.7208
B7: 2420 | C7: Remove Concrete Flatwork | E7: 6663.7263 | F7: 17303 | G7: SF | I7: 0 | J7: 3351.4377 | K7: 3312.2886 | L7: 0 | M7: 0 | N7: 0
B8: 2490 | C8: Dump Fees | E8: 2850.6692 | F8: 432.575 | G8: TON | I8: 0 | J8: 0 | K8: 0 | L8: 2850.6692 | M8: 0 | N8: 0
B9: 2150 | C9: Export Trucking | E9: 6560.7208 | F9: 432.575 | G9: TON | I9: 0 | J9: 0 | K9: 0 | L9: 0 | M9: 0 | N9: 6560.7208
C10: Remove Asphalt SF (03") | E10: 98784.182 | F10: 147064 | G10: SF | I10: 0 | J10: 19939.495 | K10: 19706.576 | L10: 17316.786 | M10: 0 | N10: 41821.325
B11: 2410 | C11: Remove Asphalt | E11: 39646.071 | F11: 147064 | G11: SF | I11: 0 | J11: 19939.495 | K11: 19706.576 | L11: 0 | M11: 0 | N11: 0
B12: 2490 | C12: Dump Fees | E12: 17316.786 | F12: 2757.45 | G12: TON | I12: 0 | J12: 0 | K12: 0 | L12: 17316.786 | M12: 0 | N12: 0
B13: 2150 | C13: Export Trucking | E13: 41821.325 | F13: 2757.45 | G13: TON | I13: 0 | J13: 0 | K13: 0 | L13: 0 | M13: 0 | N13: 41821.325
C14: Remove Curb/Gutter 24" | E14: 11787.905 | F14: 1634 | G14: LF | I14: 0 | J14: 3164.9131 | K14: 4356.9443 | L14: 1292.1672 | M14: 0 | N14: 2973.88
B15: 2421 | C15: Remove Curb And Gutter | E15: 7521.8574 | F15: 1634 | G15: LF | I15: 0 | J15: 3164.9131 | K15: 4356.9443 | L15: 0 | M15: 0 | N15: 0
B16: 2490 | C16: Dump Fees | E16: 1292.1672 | F16: 196.08 | G16: TON | I16: 0 | J16: 0 | K16: 0 | L16: 1292.1672 | M16: 0 | N16: 0
B17: 2150 | C17: Export Trucking | E17: 2973.88 | F17: 196.08 | G17: TON | I17: 0 | J17: 0 | K17: 0 | L17: 0 | M17: 0 | N17: 2973.88
C18: Remove Chain Link Fence | E18: 2487.3841 | F18: 811 | G18: LF | I18: 0 | J18: 1721.9898 | K18: 700 | L18: 50.6875 | M18: 0 | N18: 14.706721
B19: 2401 | C19: Remove Fence | E19: 2421.9898 | F19: 811 | G19: LF | I19: 0 | J19: 1721.9898 | K19: 700 | L19: 0 | M19: 0 | N19: 0
B20: 2490 | C20: Dump Fees | E20: 50.6875 | F20: 2.0275 | G20: TON | I20: 0 | J20: 0 | K20: 0 | L20: 50.6875 | M20: 0 | N20: 0
B21: 2150 | C21: Export Trucking | E21: 14.706721 | F21: 2.0275 | G21: TON | I21: 0 | J21: 0 | K21: 0 | L21: 0 | M21: 0 | N21: 14.706721
C22: Remove PVC Pipe (08") WATER | E22: 159088.02 | F22: 3367 | G22: LF | I22: 0 | J22: 56348.018 | K22: 74276.02 | L22: 11858.05 | M22: 0 | N22: 16605.933
B23: 2450 | C23: Remove Pipe | E23: 130624.04 | F23: 3367 | G23: LF | I23: 0 | J23: 56348.018 | K23: 74276.02 | L23: 0 | M23: 0 | N23: 0
B24: 2490 | C24: Dump Fees | E24: 480.63925 | F24: 19.22557 | G24: TON | I24: 0 | J24: 0 | K24: 0 | L24: 480.63925 | M24: 0 | N24: 0
B25: 2150 | C25: Export Trucking | E25: 139.45504 | F25: 19.22557 | G25: TON | I25: 0 | J25: 0 | K25: 0 | L25: 0 | M25: 0 | N25: 139.45504
B26: 2172 | C26: Import Efill | E26: 8464.1105 | F26: 971.1 | G26: TON | I26: 0 | J26: 0 | K26: 0 | L26: 8464.1105 | M26: 0 | N26: 0
B27: 2149 | C27: Import Trucking | E27: 8233.2391 | F27: 971.1 | G27: TON | I27: 0 | J27: 0 | K27: 0 | L27: 0 | M27: 0 | N27: 8233.2391
B28: 2150 | C28: Export Trucking | E28: 8233.2391 | F28: 971.1 | G28: TON | I28: 0 | J28: 0 | K28: 0 | L28: 0 | M28: 0 | N28: 8233.2391
B29: 2490 | C29: Dump Fees | E29: 2913.3 | F29: 971.1 | G29: TON | I29: 0 | J29: 0 | K29: 0 | L29: 2913.3 | M29: 0 | N29: 0
C30: Remove PVC Pipe (08") SEWER | E30: 63206.442 | F30: 691 | G30: LF | I30: 0 | J30: 17346.219 | K30: 22865.19 | L30: 9442.7384 | M30: 0 | N30: 13552.294
B31: 2450 | C31: Remove Pipe | E31: 40211.409 | F31: 691 | G31: LF | I31: 0 | J31: 17346.219 | K31: 22865.19 | L31: 0 | M31: 0 | N31: 0
B32: 2490 | C32: Dump Fees | E32: 98.64025 | F32: 3.94561 | G32: TON | I32: 0 | J32: 0 | K32: 0 | L32: 98.64025 | M32: 0 | N32: 0
B33: 2150 | C33: Export Trucking | E33: 28.619968 | F33: 3.94561 | G33: TON | I33: 0 | J33: 0 | K33: 0 | L33: 0 | M33: 0 | N33: 28.619968
B34: 2172 | C34: Import Efill | E34: 6951.4482 | F34: 797.55 | G34: TON | I34: 0 | J34: 0 | K34: 0 | L34: 6951.4482 | M34: 0 | N34: 0
B35: 2149 | C35: Import Trucking | E35: 6761.837 | F35: 797.55 | G35: TON | I35: 0 | J35: 0 | K35: 0 | L35: 0 | M35: 0 | N35: 6761.837
B36: 2150 | C36: Export Trucking | E36: 6761.837 | F36: 797.55 | G36: TON | I36: 0 | J36: 0 | K36: 0 | L36: 0 | M36: 0 | N36: 6761.837
B37: 2490 | C37: Dump Fees | E37: 2392.65 | F37: 797.55 | G37: TON | I37: 0 | J37: 0 | K37: 0 | L37: 2392.65 | M37: 0 | N37: 0
C38: Remove Pipe RCP 15" | E38: 32781.999 | F38: 1069 | G38: LF | I38: 0 | J38: 13417.589 | K38: 17686.605 | L38: 648.26833 | M38: 0 | N38: 1029.5361
B39: 2450 | C39: Remove Pipe | E39: 31104.194 | F39: 1069 | G39: LF | I39: 0 | J39: 13417.589 | K39: 17686.605 | L39: 0 | M39: 0 | N39: 0
B40: 2490 | C40: Dump Fees | E40: 648.26833 | F40: 67.8815 | G40: TON | I40: 0 | J40: 0 | K40: 0 | L40: 648.26833 | M40: 0 | N40: 0
B41: 2150 | C41: Export Trucking | E41: 1029.5361 | F41: 67.8815 | G41: TON | I41: 0 | J41: 0 | K41: 0 | L41: 0 | M41: 0 | N41: 1029.5361
C42: Remove Light Pole/Base | E42: 2652.0203 | F42: 12 | G42: EACH | I42: 0 | J42: 1084.6703 | K42: 1493.2 | L42: 28.65 | M42: 0 | N42: 45.5
B43: 2435 | C43: Remove Pole Base | E43: 2577.8703 | F43: 12 | G43: EACH | I43: 0 | J43: 1084.6703 | K43: 1493.2 | L43: 0 | M43: 0 | N43: 0
B44: 2490 | C44: Dump Fees | E44: 28.65 | F44: 3 | G44: TON | I44: 0 | J44: 0 | K44: 0 | L44: 28.65 | M44: 0 | N44: 0
B45: 2150 | C45: Export Trucking | E45: 45.5 | F45: 3 | G45: TON | I45: 0 | J45: 0 | K45: 0 | L45: 0 | M45: 0 | N45: 45.5
C46: Remove Fire Hydrant | E46: 2446.8078 | F46: 5 | G46: EACH | I46: 0 | J46: 1850.681 | K46: 567.5 | L46: 25 | M46: 0 | N46: 3.6268116
B47: 2400 | C47: Misc. Demolition | E47: 2418.181 | F47: 1 | G47: LS | I47: 0 | J47: 1850.681 | K47: 567.5 | L47: 0 | M47: 0 | N47: 0
B48: 2490 | C48: Dump Fees | E48: 25 | F48: 0.5 | G48: TON | I48: 0 | J48: 0 | K48: 0 | L48: 25 | M48: 0 | N48: 0
B49: 2150 | C49: Export Trucking | E49: 3.6268116 | F49: 0.5 | G49: TON | I49: 0 | J49: 0 | K49: 0 | L49: 0 | M49: 0 | N49: 3.6268116
C50: Remove Concrete Greast Trap | E50: 1253.0033 | F50: 1 | G50: EACH | I50: 0 | J50: 406.75138 | K50: 402 | L50: 170.02724 | M50: 0 | N50: 274.22464
B51: 2456 | C51: Remove Catch Basin | E51: 808.75138 | F51: 1 | G51: EACH | I51: 0 | J51: 406.75138 | K51: 402 | L51: 0 | M51: 0 | N51: 0
B52: 2490 | C52: Dump Fees | E52: 32.95 | F52: 5 | G52: TON | I52: 0 | J52: 0 | K52: 0 | L52: 32.95 | M52: 0 | N52: 0
B53: 2150 | C53: Export Trucking | E53: 75.833333 | F53: 5 | G53: TON | I53: 0 | J53: 0 | K53: 0 | L53: 0 | M53: 0 | N53: 75.833333
B54: 2172 | C54: Import Efill | E54: 101.97724 | F54: 11.7 | G54: TON | I54: 0 | J54: 0 | K54: 0 | L54: 101.97724 | M54: 0 | N54: 0
B55: 2149 | C55: Import Trucking | E55: 99.195652 | F55: 11.7 | G55: TON | I55: 0 | J55: 0 | K55: 0 | L55: 0 | M55: 0 | N55: 99.195652
B56: 2150 | C56: Export Trucking | E56: 99.195652 | F56: 11.7 | G56: TON | I56: 0 | J56: 0 | K56: 0 | L56: 0 | M56: 0 | N56: 99.195652
B57: 2490 | C57: Dump Fees | E57: 35.1 | F57: 11.7 | G57: TON | I57: 0 | J57: 0 | K57: 0 | L57: 35.1 | M57: 0 | N57: 0
C58: Remove Catch Basin 2020 | E58: 2601.6699 | F58: 7 | G58: EACH | I58: 0 | J58: 949.08656 | K58: 1306.55 | L58: 133.7 | M58: 0 | N58: 212.33333
B59: 2456 | C59: Remove Catch Basin | E59: 2255.6366 | F59: 7 | G59: EACH | I59: 0 | J59: 949.08656 | K59: 1306.55 | L59: 0 | M59: 0 | N59: 0
B60: 2490 | C60: Dump Fees | E60: 133.7 | F60: 7 | G60: TON | I60: 0 | J60: 0 | K60: 0 | L60: 133.7 | M60: 0 | N60: 0
B61: 2150 | C61: Export Trucking | E61: 212.33333 | F61: 7 | G61: TON | I61: 0 | J61: 0 | K61: 0 | L61: 0 | M61: 0 | N61: 212.33333
C62: Remove Manhole 60" | E62: 5217.7986 | F62: 5 | G62: EACH | I62: 0 | J62: 2033.7569 | K62: 2010 | L62: 453.625 | M62: 0 | N62: 720.41667
B63: 2455 | C63: Remove Manhole | E63: 4043.7569 | F63: 5 | G63: EACH | I63: 0 | J63: 2033.7569 | K63: 2010 | L63: 0 | M63: 0 | N63: 0
B64: 2490 | C64: Dump Fees | E64: 453.625 | F64: 47.5 | G64: TON | I64: 0 | J64: 0 | K64: 0 | L64: 453.625 | M64: 0 | N64: 0
B65: 2150 | C65: Export Trucking | E65: 720.41667 | F65: 47.5 | G65: TON | I65: 0 | J65: 0 | K65: 0 | L65: 0 | M65: 0 | N65: 720.41667
C66: Remove Water Meter 2020 | E66: 1298.5391 | F66: 2 | G66: EACH | I66: 0 | J66: 555.20429 | K66: 170.25 | L66: 340.59204 | M66: 0 | N66: 232.49275
B67: 2400 | C67: Misc. Demolition | E67: 725.45429 | F67: 1 | G67: LS | I67: 0 | J67: 555.20429 | K67: 170.25 | L67: 0 | M67: 0 | N67: 0
B68: 2490 | C68: Dump Fees | E68: 200 | F68: 4 | G68: TON | I68: 0 | J68: 0 | K68: 0 | L68: 200 | M68: 0 | N68: 0
B69: 2150 | C69: Export Trucking | E69: 29.014493 | F69: 4 | G69: TON | I69: 0 | J69: 0 | K69: 0 | L69: 0 | M69: 0 | N69: 29.014493
B70: 2172 | C70: Import Efill | E70: 104.59204 | F70: 12 | G70: TON | I70: 0 | J70: 0 | K70: 0 | L70: 104.59204 | M70: 0 | N70: 0
B71: 2149 | C71: Import Trucking | E71: 101.73913 | F71: 12 | G71: TON | I71: 0 | J71: 0 | K71: 0 | L71: 0 | M71: 0 | N71: 101.73913
B72: 2150 | C72: Export Trucking | E72: 101.73913 | F72: 12 | G72: TON | I72: 0 | J72: 0 | K72: 0 | L72: 0 | M72: 0 | N72: 101.73913
B73: 2490 | C73: Dump Fees | E73: 36 | F73: 12 | G73: TON | I73: 0 | J73: 0 | K73: 0 | L73: 36 | M73: 0 | N73: 0
C74: Remove Basketball Standard | E74: 991.41805 | F74: 4 | G74: EACH | I74: 0 | J74: 406.75138 | K74: 559.95 | L74: 9.55 | M74: 0 | N74: 15.166667
B75: 2435 | C75: Remove Pole Base | E75: 966.70138 | F75: 4 | G75: EACH | I75: 0 | J75: 406.75138 | K75: 559.95 | L75: 0 | M75: 0 | N75: 0
B76: 2490 | C76: Dump Fees | E76: 9.55 | F76: 1 | G76: TON | I76: 0 | J76: 0 | K76: 0 | L76: 9.55 | M76: 0 | N76: 0
B77: 2150 | C77: Export Trucking | E77: 15.166667 | F77: 1 | G77: TON | I77: 0 | J77: 0 | K77: 0 | L77: 0 | M77: 0 | N77: 15.166667
C78: Demo Bollard | E78: 4941.0501 | F78: 32 | G78: EACH | I78: 0 | J78: 2033.7569 | K78: 2799.75 | L78: 61.12 | M78: 0 | N78: 46.423188
B79: 2400 | C79: Misc. Demolition | E79: 4833.5069 | F79: 1 | G79: LS | I79: 0 | J79: 2033.7569 | K79: 2799.75 | L79: 0 | M79: 0 | N79: 0
B80: 2490 | C80: Dump Fees | E80: 61.12 | F80: 6.4 | G80: TON | I80: 0 | J80: 0 | K80: 0 | L80: 61.12 | M80: 0 | N80: 0
B81: 2150 | C81: Export Trucking | E81: 46.423188 | F81: 6.4 | G81: TON | I81: 0 | J81: 0 | K81: 0 | L81: 0 | M81: 0 | N81: 46.423188
A82: 3 | C82: Site Earthwork | E82: 912203.67 | F82: 1 | G82: LS | H82: 1267100 | I82: 0 | J82: 100773.18 | K82: 227535.16 | L82: 156571.49 | M82: 0 | N82: 427323.85
C83: Strip & Stockpile Topsoil Onsite Phase 1 | E83: 16412.94 | F83: 4500 | G83: CY | I83: 0 | J83: 4241.5116 | K83: 12171.429 | L83: 0 | M83: 0 | N83: 0
B84: 2120 | C84: Strip Topsoil | E84: 16412.94 | F84: 4500 | G84: CY | I84: 0 | J84: 4241.5116 | K84: 12171.429 | L84: 0 | M84: 0 | N84: 0
C85: KSC Cut To Fill (D8/D6/621/563) Phase 1 | E85: 29598.114 | F85: 3033 | G85: CY | I85: 0 | J85: 6927.8023 | K85: 22320 | L85: 350.3115 | M85: 0 | N85: 0
B86: 2130 | C86: Cut To Fill | E86: 29598.114 | F86: 3033 | G86: CY | I86: 0 | J86: 6927.8023 | K86: 22320 | L86: 350.3115 | M86: 0 | N86: 0
C87: Import A1A Compacted CY Phase 1 | E87: 336393.34 | F87: 9706 | G87: CY | I87: 0 | J87: 16166.438 | K87: 19829.358 | L87: 152275.55 | M87: 0 | N87: 148122
B88: 2129 | C88: Place Fill | E88: 35995.796 | F88: 17470.8 | G88: TON | I88: 0 | J88: 16166.438 | K88: 19829.358 | L88: 0 | M88: 0 | N88: 0
B89: 2172 | C89: Import Efill | E89: 152275.55 | F89: 17470.8 | G89: TON | I89: 0 | J89: 0 | K89: 0 | L89: 152275.55 | M89: 0 | N89: 0
B90: 2149 | C90: Import Trucking | E90: 148122 | F90: 17470.8 | G90: TON | I90: 0 | J90: 0 | K90: 0 | L90: 0 | M90: 0 | N90: 148122
C91: Fine Grade Roadway (140/563) Phase 1 | E91: 28753.235 | F91: 309531 | G91: SF | I91: 0 | J91: 12729.847 | K91: 15373.373 | L91: 650.0151 | M91: 0 | N91: 0
B92: 2135 | C92: Fine Grade | E92: 28103.22 | F92: 309531 | G92: SF | I92: 0 | J92: 12729.847 | K92: 15373.373 | L92: 0 | M92: 0 | N92: 0
B93: 1410 | C93: Construction Water | E93: 650.0151 | F93: 185.7186 | G93: MGAL | I93: 0 | J93: 0 | K93: 0 | L93: 650.0151 | M93: 0 | N93: 0
C94: KSC Cut To Fill (D8/D6/621/563) Phase 2 | E94: 14824.063 | F94: 1733 | G94: CY | I94: 0 | J94: 3463.9011 | K94: 11160 | L94: 200.1615 | M94: 0 | N94: 0
B95: 2130 | C95: Cut To Fill | E95: 14824.063 | F95: 1733 | G95: CY | I95: 0 | J95: 3463.9011 | K95: 11160 | L95: 200.1615 | M95: 0 | N95: 0
C96: KSC Cut To Stockpile Phase 2 | E96: 143821.35 | F96: 18818 | G96: CY | I96: 0 | J96: 31039.853 | K96: 110608.02 | L96: 2173.479 | M96: 0 | N96: 0
B97: 2130 | C97: Cut To Fill | E97: 143821.35 | F97: 18818 | G97: CY | I97: 0 | J97: 31039.853 | K97: 110608.02 | L97: 2173.479 | M97: 0 | N97: 0
C98: Load & Export Spoils | E98: 301617.38 | F98: 18818 | G98: CY | I98: 0 | J98: 8147.9615 | K98: 14267.572 | L98: 0 | M98: 0 | N98: 279201.85
B99: 2500 | C99: Loading Trucks | E99: 22415.534 | F99: 32931.5 | G99: TON | I99: 0 | J99: 8147.9615 | K99: 14267.572 | L99: 0 | M99: 0 | N99: 0
B100: 2150 | C100: Export Trucking | E100: 279201.85 | F100: 32931.5 | G100: TON | I100: 0 | J100: 0 | K100: 0 | L100: 0 | M100: 0 | N100: 279201.85
...
